Workbook

Sheet 00_maestro_productos
A1: id_producto | B1: producto | C1: categoria | D1: coste_objetivo | E1: precio_venta_recomendado | F1: margen_objetivo_pct
A2: P001 | B2: Auriculares inalámbricos | C2: Electrónica | D2: 84.31 | E2: 122.19 | F2: 0.31
A3: P002 | B3: Smartwatch | C3: Electrónica | D3: 47.23 | E3: 73.8 | F3: 0.36
A4: P003 | B4: Tablet 10" | C4: Electrónica | D4: 94.19 | E4: 177.72 | F4: 0.47
A5: P004 | B5: Altavoz Bluetooth | C5: Electrónica | D5: 110.03 | E5: 161.81 | F5: 0.32
A6: P005 | B6: Robot de cocina | C6: Hogar | D6: 41.17 | E6: 59.67 | F6: 0.31
A7: P006 | B7: Set de sartenes | C7: Hogar | D7: 26.63 | E7: 46.72 | F7: 0.43
A8: P007 | B8: Aspiradora sin cable | C8: Hogar | D8: 12.9 | E8: 19.85 | F8: 0.35
A9: P008 | B9: Lámpara LED de pie | C9: Hogar | D9: 57.47 | E9: 102.62 | F9: 0.44
A10: P009 | B10: Aceite de oliva virgen extra 1L | C10: Alimentación | D10: 4.32 | E10: 7.85 | F10: 0.45
A11: P010 | B11: Cava brut nature | C11: Alimentación | D11: 11.44 | E11: 16.34 | F11: 0.3
A12: P011 | B12: Café en grano 1kg | C12: Alimentación | D12: 11.4 | E12: 21.51 | F12: 0.47
A13: P012 | B13: Chocolate a la taza 500g | C13: Alimentación | D13: 5.77 | E13: 8.74 | F13: 0.34
... A21: P020 | B21: Set de maquillaje | C21: Perfumería y Belleza | D21: 33.78 | E21: 60.32 | F21: 0.44

Sheet 01_datos_crudos
A1: id_venta | B1: fecha | C1: año | D1: mes | E1: nombre_mes | F1: trimestre | G1: id_producto | H1: producto | I1: gama | J1: categoria | K1: cantidad | L1: precio_unitario | M1: coste_unitario | N1: descuento_pct | O1: ingresos | P1: costes | Q1: beneficio | R1: beneficio_pct | S1: comunidad_autonoma | T1: canal
A2: V00557 | B2: 45785 | C2: =YEAR(Tabla2[[#This Row],[fecha]]) -> 2025 | D2: =MONTH(Tabla2[[#This Row],[fecha]]) -> 5 | E2: =TEXT(Tabla2[[#This Row],[fecha]], "mmmm") -> mayo | F2: =F3 -> T3 | G2: P006 | H2: Set de sartenes | I2: =IF(Tabla2[[#This Row],[precio_unitario]]<=30,"Económico",IF(Tabla2[[#This Row],[precio_unitario]]<=58.49,"Accesible","Caro")) -> Accesible | J2: Hogar | K2: 7 | L2: 48.85 | M2: 26.46 | N2: 0 | O2: =K2*L2*(1-N2) -> 341.95 | P2: =M2*K2 -> 185.22 | Q2: =O2-P2 -> 156.73 | R2: =IFERROR(Q2/O2,0) -> 0.45834186 | S2: C. Valenciana | T2: online
A3: V01049 | B3: 45540 | C3: =YEAR(Tabla2[[#This Row],[fecha]]) -> 2024 | D3: =MONTH(Tabla2[[#This Row],[fecha]]) -> 9 | E3: =TEXT(Tabla2[[#This Row],[fecha]], "mmmm") -> septiembre | F3: ="T"&ROUNDUP(Tabla2[[#This Row],[mes]]/3,0) -> T3 | G3: P010 | H3: Cava brut nature | I3: =IF(Tabla2[[#This Row],[precio_unitario]]<=30,"Económico",IF(Tabla2[[#This Row],[precio_unitario]]<=58.49,"Accesible","Caro")) -> Económico | J3: Alimentación | K3: 4 | L3: 17.33 | M3: 10.93 | N3: 0 | O3: =K3*L3*(1-N3) -> 69.32 | P3: =M3*K3 -> 43.72 | Q3: =O3-P3 -> 25.6 | R3: =IFERROR(Q3/O3,0) -> 0.36930179 | S3: Sin dato | T3: online
A4: V00142 | B4: 45764 | C4: =YEAR(Tabla2[[#This Row],[fecha]]) -> 2025 | D4: =MONTH(Tabla2[[#This Row],[fecha]]) -> 4 | E4: =TEXT(Tabla2[[#This Row],[fecha]], "mmmm") -> abril | F4: ="T"&ROUNDUP(Tabla2[[#This Row],[mes]]/3,0) -> T2 | G4: P015 | H4: Zapatillas running | I4: =IF(Tabla2[[#This Row],[precio_unitario]]<=30,"Económico",IF(Tabla2[[#This Row],[precio_unitario]]<=58.49,"Accesible","Caro")) -> Caro | J4: Moda | K4: 3 | L4: 73.59 | M4: 41.51 | N4: 0 | O4: =K4*L4*(1-N4) -> 220.77 | P4: =M4*K4 -> 124.53 | Q4: =O4-P4 -> 96.24 | R4: =IFERROR(Q4/O4,0) -> 0.43592879 | S4: Baleares | T4: tienda_fisica
A5: V00916 | B5: 45428 | C5: =YEAR(Tabla2[[#This Row],[fecha]]) -> 2024 | D5: =MONTH(Tabla2[[#This Row],[fecha]]) -> 5 | E5: =TEXT(Tabla2[[#This Row],[fecha]], "mmmm") -> mayo | F5: ="T"&ROUNDUP(Tabla2[[#This Row],[mes]]/3,0) -> T2 | G5: P002 | H5: Smartwatch | I5: =IF(Tabla2[[#This Row],[precio_unitario]]<=30,"Económico",IF(Tabla2[[#This Row],[precio_unitario]]<=58.49,"Accesible","Caro")) -> Caro | J5: Electrónica | K5: 1 | L5: 75.75 | M5: 46.12 | N5: 0 | O5: =K5*L5*(1-N5) -> 75.75 | P5: =M5*K5 -> 46.12 | Q5: =O5-P5 -> 29.63 | R5: =IFERROR(Q5/O5,0) -> 0.39115512 | S5: C. Valenciana | T5: tienda_fisica
A6: V00003 | B6: 45993 | C6: =YEAR(Tabla2[[#This Row],[fecha]]) -> 2025 | D6: =MONTH(Tabla2[[#This Row],[fecha]]) -> 12 | E6: =TEXT(Tabla2[[#This Row],[fecha]], "mmmm") -> diciembre | F6: ="T"&ROUNDUP(Tabla2[[#This Row],[mes]]/3,0) -> T4 | G6: P008 | H6: Lámpara LED de pie | I6: =IF(Tabla2[[#This Row],[precio_unitario]]<=30,"Económico",IF(Tabla2[[#This Row],[precio_unitario]]<=58.49,"Accesible","Caro")) -> Caro | J6: Hogar | K6: 1 | L6: 107.63 | M6: 56.9 | N6: 0.28 | O6: =K6*L6*(1-N6) -> 77.4936 | P6: =M6*K6 -> 56.9 | Q6: =O6-P6 -> 20.5936 | R6: =IFERROR(Q6/O6,0) -> 0.26574582 | S6: Cataluña | T6: tienda_fisica
A7: V00579 | B7: 45531 | C7: =YEAR(Tabla2[[#This Row],[fecha]]) -> 2024 | D7: =MONTH(Tabla2[[#This Row],[fecha]]) -> 8 | E7: =TEXT(Tabla2[[#This Row],[fecha]], "mmmm") -> agosto | F7: ="T"&ROUNDUP(Tabla2[[#This Row],[mes]]/3,0) -> T3 | G7: P018 | H7: Crema facial hidratante | I7: =IF(Tabla2[[#This Row],[precio_unitario]]<=30,"Económico",IF(Tabla2[[#This Row],[precio_unitario]]<=58.49,"Accesible","Caro")) -> Accesible | J7: Perfumería y Belleza | K7: 3 | L7: 32.74 | M7: 16.47 | N7: 0 | O7: =K7*L7*(1-N7) -> 98.22 | P7: =M7*K7 -> 49.41 | Q7: =O7-P7 -> 48.81 | R7: =IFERROR(Q7/O7,0) -> 0.49694563 | S7: Cataluña | T7: tienda_fisica
A8: V00712 | B8: 45695 | C8: =YEAR(Tabla2[[#This Row],[fecha]]) -> 2025 | D8: =MONTH(Tabla2[[#This Row],[fecha]]) -> 2 | E8: =TEXT(Tabla2[[#This Row],[fecha]], "mmmm") -> febrero | F8: ="T"&ROUNDUP(Tabla2[[#This Row],[mes]]/3,0) -> T1 | G8: P004 | H8: Altavoz Bluetooth | I8: =IF(Tabla2[[#This Row],[precio_unitario]]<=30,"Económico",IF(Tabla2[[#This Row],[precio_unitario]]<=58.49,"Accesible","Caro")) -> Caro | J8: Electrónica | K8: 1 | L8: 149.61 | M8: =INDEX(Tabla3[coste_objetivo], MATCH(Tabla2[[#This Row],[id_producto]], Tabla3[id_producto],0)) -> 110.03 | N8: 0 | O8: =K8*L8*(1-N8) -> 149.61 | P8: =M8*K8 -> 110.03 | Q8: =O8-P8 -> 39.58 | R8: =IFERROR(Q8/O8,0) -> 0.26455451 | S8: Cataluña | T8: tienda_fisica
A9: V00152 | B9: 45760 | C9: =YEAR(Tabla2[[#This Row],[fecha]]) -> 2025 | D9: =MONTH(Tabla2[[#This Row],[fecha]]) -> 4 | E9: =TEXT(Tabla2[[#This Row],[fecha]], "mmmm") -> abril | F9: ="T"&ROUNDUP(Tabla2[[#This Row],[mes]]/3,0) -> T2 | G9: P003 | H9: Tablet 10" | I9: =IF(Tabla2[[#This Row],[precio_unitario]]<=30,"Económico",IF(Tabla2[[#This Row],[precio_unitario]]<=58.49,"Accesible","Caro")) -> Caro | J9: Electrónica | K9: 6 | L9: 172.48 | M9: 92.4 | N9: 0 | O9: =K9*L9*(1-N9) -> 1034.88 | P9: =M9*K9 -> 554.4 | Q9: =O9-P9 -> 480.48 | R9: =IFERROR(Q9/O9,0) -> 0.46428571 | S9: Cataluña | T9: online
A10: V00268 | B10: 45793 | C10: =YEAR(Tabla2[[#This Row],[fecha]]) -> 2025 | D10: =MONTH(Tabla2[[#This Row],[fecha]]) -> 5 | E10: =TEXT(Tabla2[[#This Row],[fecha]], "mmmm") -> mayo | F10: ="T"&ROUNDUP(Tabla2[[#This Row],[mes]]/3,0) -> T2 | G10: P013 | H10: Camiseta básica algodón | I10: =IF(Tabla2[[#This Row],[precio_unitario]]<=30,"Económico",IF(Tabla2[[#This Row],[precio_unitario]]<=58.49,"Accesible","Caro")) -> Caro | J10: Moda | K10: 4 | L10: 71.59 | M10: 49.02 | N10: 0 | O10: =K10*L10*(1-N10) -> 286.36 | P10: =M10*K10 -> 196.08 | Q10: =O10-P10 -> 90.28 | R10: =IFERROR(Q10/O10,0) -> 0.3152675 | S10: Cataluña | T10: tienda_fisica
A11: V01897 | B11: 45755 | C11: =YEAR(Tabla2[[#This Row],[fecha]]) -> 2025 | D11: =MONTH(Tabla2[[#This Row],[fecha]]) -> 4 | E11: =TEXT(Tabla2[[#This Row],[fecha]], "mmmm") -> abril | F11: ="T"&ROUNDUP(Tabla2[[#This Row],[mes]]/3,0) -> T2 | G11: P015 | H11: Zapatillas running | I11: =IF(Tabla2[[#This Row],[precio_unitario]]<=30,"Económico",IF(Tabla2[[#This Row],[precio_unitario]]<=58.49,"Accesible","Caro")) -> Caro | J11: Moda | K11: 4 | L11: 74 | M11: 40.67 | N11: 0 | O11: =K11*L11*(1-N11) -> 296 | P11: =M11*K11 -> 162.68 | Q11: =O11-P11 -> 133.32 | R11: =IFERROR(Q11/O11,0) -> 0.45040541 | S11: Cataluña | T11: tienda_fisica
A12: V00263 | B12: 45851 | C12: =YEAR(Tabla2[[#This Row],[fecha]]) -> 2025 | D12: =MONTH(Tabla2[[#This Row],[fecha]]) -> 7 | E12: =TEXT(Tabla2[[#This Row],[fecha]], "mmmm") -> julio | F12: ="T"&ROUNDUP(Tabla2[[#This Row],[mes]]/3,0) -> T3 | G12: P015 | H12: Zapatillas running | I12: =IF(Tabla2[[#This Row],[precio_unitario]]<=30,"Económico",IF(Tabla2[[#This Row],[precio_unitario]]<=58.49,"Accesible","Caro")) -> Caro | J12: Moda | K12: 5 | L12: 74.66 | M12: 44.39 | N12: 0.12 | O12: =K12*L12*(1-N12) -> 328.504 | P12: =M12*K12 -> 221.95 | Q12: =O12-P12 -> 106.554 | R12: =IFERROR(Q12/O12,0) -> 0.32436135 | S12: Cataluña | T12: tienda_fisica
A13: V00880 | B13: 45314 | C13: =YEAR(Tabla2[[#This Row],[fecha]]) -> 2024 | D13: =MONTH(Tabla2[[#This Row],[fecha]]) -> 1 | E13: =TEXT(Tabla2[[#This Row],[fecha]], "mmmm") -> enero | F13: ="T"&ROUNDUP(Tabla2[[#This Row],[mes]]/3,0) -> T1 | G13: P006 | H13: Set de sartenes | I13: =IF(Tabla2[[#This Row],[precio_unitario]]<=30,"Económico",IF(Tabla2[[#This Row],[precio_unitario]]<=58.49,"Accesible","Caro")) -> Accesible | J13: Hogar | K13: 4 | L13: 48.65 | M13: 26.34 | N13: 0 | O13: =K13*L13*(1-N13) -> 194.6 | P13: =M13*K13 -> 105.36 | Q13: =O13-P13 -> 89.24 | R13: =IFERROR(Q13/O13,0) -> 0.45858171 | S13: C. Valenciana | T13: online
A14: V01030 | B14: 45359 | C14: =YEAR(Tabla2[[#This Row],[fecha]]) -> 2024 | D14: =MONTH(Tabla2[[#This Row],[fecha]]) -> 3 | E14: =TEXT(Tabla2[[#This Row],[fecha]], "mmmm") -> marzo | F14: ="T"&ROUNDUP(Tabla2[[#This Row],[mes]]/3,0) -> T1 | G14: P008 | H14: Lámpara LED de pie | I14: =IF(Tabla2[[#This Row],[precio_unitario]]<=30,"Económico",IF(Tabla2[[#This Row],[precio_unitario]]<=58.49,"Accesible","Caro")) -> Caro | J14: Hogar | K14: 10 | L14: 101.05 | M14: 56.85 | N14: 0 | O14: =K14*L14*(1-N14) -> 1010.5 | P14: =M14*K14 -> 568.5 | Q14: =O14-P14 -> 442 | R14: =IFERROR(Q14/O14,0) -> 0.43740722 | S14: C. Valenciana | T14: online
A15: V01643 | B15: 45531 | C15: =YEAR(Tabla2[[#This Row],[fecha]]) -> 2024 | D15: =MONTH(Tabla2[[#This Row],[fecha]]) -> 8 | E15: =TEXT(Tabla2[[#This Row],[fecha]], "mmmm") -> agosto | F15: ="T"&ROUNDUP(Tabla2[[#This Row],[mes]]/3,0) -> T3 | G15: P015 | H15: Zapatillas running | I15: =IF(Tabla2[[#This Row],[precio_unitario]]<=30,"Económico",IF(Tabla2[[#This Row],[precio_unitario]]<=58.49,"Accesible","Caro")) -> Caro | J15: Moda | K15: 1 | L15: 74.6 | M15: 41.14 | N15: 0 | O15: =K15*L15*(1-N15) -> 74.6 | P15: =M15*K15 -> 41.14 | Q15: =O15-P15 -> 33.46 | R15: =IFERROR(Q15/O15,0) -> 0.44852547 | S15: Baleares | T15: tienda_fisica
A16: V01125 | B16: 45736 | C16: =YEAR(Tabla2[[#This Row],[fecha]]) -> 2025 | D16: =MONTH(Tabla2[[#This Row],[fecha]]) -> 3 | E16: =TEXT(Tabla2[[#This Row],[fecha]], "mmmm") -> marzo | F16: ="T"&ROUNDUP(Tabla2[[#This Row],[mes]]/3,0) -> T1 | G16: P001 | H16: Auriculares inalámbricos | I16: =IF(Tabla2[[#This Row],[precio_unitario]]<=30,"Económico",IF(Tabla2[[#This Row],[precio_unitario]]<=58.49,"Accesible","Caro")) -> Caro | J16: Electrónica | K16: 1 | L16: 120.59 | M16: 82.31 | N16: 0 | O16: =K16*L16*(1-N16) -> 120.59 | P16: =M16*K16 -> 82.31 | Q16: =O16-P16 -> 38.28 | R16: =IFERROR(Q16/O16,0) -> 0.31743926 | S16: Cataluña | T16: tienda_fisica
A17: V01862 | B17: 45534 | C17: =YEAR(Tabla2[[#This Row],[fecha]]) -> 2024 | D17: =MONTH(Tabla2[[#This Row],[fecha]]) -> 8 | E17: =TEXT(Tabla2[[#This Row],[fecha]], "mmmm") -> agosto | F17: ="T"&ROUNDUP(Tabla2[[#This Row],[mes]]/3,0) -> T3 | G17: P011 | H17: Café en grano 1kg | I17: =IF(Tabla2[[#This Row],[precio_unitario]]<=30,"Económico",IF(Tabla2[[#This Row],[precio_unitario]]<=58.49,"Accesible","Caro")) -> Económico | J17: Alimentación | K17: 5 | L17: 20.02 | M17: =INDEX(Tabla3[coste_objetivo], MATCH(Tabla2[[#This Row],[id_producto]], Tabla3[id_producto],0)) -> 11.4 | N17: 0 | O17: =K17*L17*(1-N17) -> 100.1 | P17: =M17*K17 -> 57 | Q17: =O17-P17 -> 43.1 | R17: =IFERROR(Q17/O17,0) -> 0.43056943 | S17: C. Valenciana | T17: tienda_fisica
A18: V00201 | B18: 45842 | C18: =YEAR(Tabla2[[#This Row],[fecha]]) -> 2025 | D18: =MONTH(Tabla2[[#This Row],[fecha]]) -> 7 | E18: =TEXT(Tabla2[[#This Row],[fecha]], "mmmm") -> julio | F18: ="T"&ROUNDUP(Tabla2[[#This Row],[mes]]/3,0) -> T3 | G18: P016 | H18: Bolso bandolera | I18: =IF(Tabla2[[#This Row],[precio_unitario]]<=30,"Económico",IF(Tabla2[[#This Row],[precio_unitario]]<=58.49,"Accesible","Caro")) -> Caro | J18: Moda | K18: 6 | L18: 80.08 | M18: 42.19 | N18: 0 | O18: =K18*L18*(1-N18) -> 480.48 | P18: =M18*K18 -> 253.14 | Q18: =O18-P18 -> 227.34 | R18: =IFERROR(Q18/O18,0) -> 0.47315185 | S18: Baleares | T18: tienda_fisica
A19: V02278 | B19: 45657 | C19: =YEAR(Tabla2[[#This Row],[fecha]]) -> 2024 | D19: =MONTH(Tabla2[[#This Row],[fecha]]) -> 12 | E19: =TEXT(Tabla2[[#This Row],[fecha]], "mmmm") -> diciembre | F19: ="T"&ROUNDUP(Tabla2[[#This Row],[mes]]/3,0) -> T4 | G19: P018 | H19: Crema facial hidratante | I19: =IF(Tabla2[[#This Row],[precio_unitario]]<=30,"Económico",IF(Tabla2[[#This Row],[precio_unitario]]<=58.49,"Accesible","Caro")) -> Económico | J19: Perfumería y Belleza | K19: 3 | L19: 29.76 | M19: 17.11 | N19: 0 | O19: =K19*L19*(1-N19) -> 89.28 | P19: =M19*K19 -> 51.33 | Q19: =O19-P19 -> 37.95 | R19: =IFERROR(Q19/O19,0) -> 0.4250672 | S19: Cataluña | T19: tienda_fisica
A20: V01650 | B20: 45990 | C20: =YEAR(Tabla2[[#This Row],[fecha]]) -> 2025 | D20: =MONTH(Tabla2[[#This Row],[fecha]]) -> 11 | E20: =TEXT(Tabla2[[#This Row],[fecha]], "mmmm") -> noviembre | F20: ="T"&ROUNDUP(Tabla2[[#This Row],[mes]]/3,0) -> T4 | G20: P018 | H20: Crema facial hidratante | I20: =IF(Tabla2[[#This Row],[precio_unitario]]<=30,"Económico",IF(Tabla2[[#This Row],[precio_unitario]]<=58.49,"Accesible","Caro")) -> Accesible | J20: Perfumería y Belleza | K20: 4 | L20: 31.14 | M20: 16.47 | N20: 0 | O20: =K20*L20*(1-N20) -> 124.56 | P20: =M20*K20 -> 65.88 | Q20: =O20-P20 -> 58.68 | R20: =IFERROR(Q20/O20,0) -> 0.47109827 | S20: Cataluña | T20: tienda_fisica
A21: V00833 | B21: 45345 | C21: =YEAR(Tabla2[[#This Row],[fecha]]) -> 2024 | D21: =MONTH(Tabla2[[#This Row],[fecha]]) -> 2 | E21: =TEXT(Tabla2[[#This Row],[fecha]], "mmmm") -> febrero | F21: ="T"&ROUNDUP(Tabla2[[#This Row],[mes]]/3,0) -> T1 | G21: P015 | H21: Zapatillas running | I21: =IF(Tabla2[[#This Row],[precio_unitario]]<=30,"Económico",IF(Tabla2[[#This Row],[precio_unitario]]<=58.49,"Accesible","Caro")) -> Caro | J21: Moda | K21: 2 | L21: 74.68 | M21: =INDEX(Tabla3[coste_objetivo], MATCH(Tabla2[[#This Row],[id_producto]], Tabla3[id_producto],0)) -> 42.79 | N21: 0.05 | O21: =K21*L21*(1-N21) -> 141.892 | P21: =M21*K21 -> 85.58 | Q21: =O21-P21 -> 56.312 | R21: =IFERROR(Q21/O21,0) -> 0.39686522 | S21: Madrid | T21: online
A22: V00849 | B22: 45681 | C22: =YEAR(Tabla2[[#This Row],[fecha]]) -> 2025 | D22: =MONTH(Tabla2[[#This Row],[fecha]]) -> 1 | E22: =TEXT(Tabla2[[#This Row],[fecha]], "mmmm") -> enero | F22: ="T"&ROUNDUP(Tabla2[[#This Row],[mes]]/3,0) -> T1 | G22: P009 | H22: Aceite de oliva virgen extra 1L | I22: =IF(Tabla2[[#This Row],[precio_unitario]]<=30,"Económico",IF(Tabla2[[#This Row],[precio_unitario]]<=58.49,"Accesible","Caro")) -> Económico | J22: Alimentación | K22: 2 | L22: 7.31 | M22: 4.16 | N22: 0 | O22: =K22*L22*(1-N22) -> 14.62 | P22: =M22*K22 -> 8.32 | Q22: =O22-P22 -> 6.3 | R22: =IFERROR(Q22/O22,0) -> 0.43091655 | S22: Sin dato | T22: tienda_fisica
A23: V00233 | B23: 45458 | C23: =YEAR(Tabla2[[#This Row],[fecha]]) -> 2024 | D23: =MONTH(Tabla2[[#This Row],[fecha]]) -> 6 | E23: =TEXT(Tabla2[[#This Row],[fecha]], "mmmm") -> junio | F23: ="T"&ROUNDUP(Tabla2[[#This Row],[mes]]/3,0) -> T2 | G23: P010 | H23: Cava brut nature | I23: =IF(Tabla2[[#This Row],[precio_unitario]]<=30,"Económico",IF(Tabla2[[#This Row],[precio_unitario]]<=58.49,"Accesible","Caro")) -> Económico | J23: Alimentación | K23: 8 | L23: 16.45 | M23: 11.31 | N23: 0 | O23: =K23*L23*(1-N23) -> 131.6 | P23: =M23*K23 -> 90.48 | Q23: =O23-P23 -> 41.12 | R23: =IFERROR(Q23/O23,0) -> 0.31246201 | S23: Madrid | T23: tienda_fisica
A24: V00401 | B24: 45709 | C24: =YEAR(Tabla2[[#This Row],[fecha]]) -> 2025 | D24: =MONTH(Tabla2[[#This Row],[fecha]]) -> 2 | E24: =TEXT(Tabla2[[#This Row],[fecha]], "mmmm") -> febrero | F24: ="T"&ROUNDUP(Tabla2[[#This Row],[mes]]/3,0) -> T1 | G24: P009 | H24: Aceite de oliva virgen extra 1L | I24: =IF(Tabla2[[#This Row],[precio_unitario]]<=30,"Económico",IF(Tabla2[[#This Row],[precio_unitario]]<=58.49,"Accesible","Caro")) -> Económico | J24: Alimentación | K24: 2 | L24: 8.07 | M24: 4.34 | N24: 0 | O24: =K24*L24*(1-N24) -> 16.14 | P24: =M24*K24 -> 8.68 | Q24: =O24-P24 -> 7.46 | R24: =IFERROR(Q24/O24,0) -> 0.4622057 | S24: C. Valenciana | T24: tienda_fisica
A25: V00864 | B25: 45973 | C25: =YEAR(Tabla2[[#This Row],[fecha]]) -> 2025 | D25: =MONTH(Tabla2[[#This Row],[fecha]]) -> 11 | E25: =TEXT(Tabla2[[#This Row],[fecha]], "mmmm") -> noviembre | F25: ="T"&ROUNDUP(Tabla2[[#This Row],[mes]]/3,0) -> T4 | G25: P012 | H25: Chocolate a la taza 500g | I25: =IF(Tabla2[[#This Row],[precio_unitario]]<=30,"Económico",IF(Tabla2[[#This Row],[precio_unitario]]<=58.49,"Accesible","Caro")) -> Económico | J25: Alimentación | K25: 8 | L25: 8.08 | M25: 5.55 | N25: 0 | O25: =K25*L25*(1-N25) -> 64.64 | P25: =M25*K25 -> 44.4 | Q25: =O25-P25 -> 20.24 | R25: =IFERROR(Q25/O25,0) -> 0.31311881 | S25: C. Valenciana | T25: tienda_fisica
A26: V01681 | B26: 45478 | C26: =YEAR(Tabla2[[#This Row],[fecha]]) -> 2024 | D26: =MONTH(Tabla2[[#This Row],[fecha]]) -> 7 | E26: =TEXT(Tabla2[[#This Row],[fecha]], "mmmm") -> julio | F26: ="T"&ROUNDUP(Tabla2[[#This Row],[mes]]/3,0) -> T3 | G26: P018 | H26: Crema facial hidratante | I26: =IF(Tabla2[[#This Row],[precio_unitario]]<=30,"Económico",IF(Tabla2[[#This Row],[precio_unitario]]<=58.49,"Accesible","Caro")) -> Accesible | J26: Perfumería y Belleza | K26: 1 | L26: 31.49 | M26: 17.11 | N26: 0 | O26: =K26*L26*(1-N26) -> 31.49 | P26: =M26*K26 -> 17.11 | Q26: =O26-P26 -> 14.38 | R26: =IFERROR(Q26/O26,0) -> 0.45665291 | S26: Madrid | T26: online
A27: V01924 | B27: 46007 | C27: =YEAR(Tabla2[[#This Row],[fecha]]) -> 2025 | D27: =MONTH(Tabla2[[#This Row],[fecha]]) -> 12 | E27: =TEXT(Tabla2[[#This Row],[fecha]], "mmmm") -> diciembre | F27: ="T"&ROUNDUP(Tabla2[[#This Row],[mes]]/3,0) -> T4 | G27: P019 | H27: Champú reparador | I27: =IF(Tabla2[[#This Row],[precio_unitario]]<=30,"Económico",IF(Tabla2[[#This Row],[precio_unitario]]<=58.49,"Accesible","Caro")) -> Accesible | J27: Perfumería y Belleza | K27: 4 | L27: 58.3 | M27: 32.06 | N27: 0.18 | O27: =K27*L27*(1-N27) -> 191.224 | P27: =M27*K27 -> 128.24 | Q27: =O27-P27 -> 62.984 | R27: =IFERROR(Q27/O27,0) -> 0.32937288 | S27: Madrid | T27: online
A28: V00652 | B28: 45496 | C28: =YEAR(Tabla2[[#This Row],[fecha]]) -> 2024 | D28: =MONTH(Tabla2[[#This Row],[fecha]]) -> 7 | E28: =TEXT(Tabla2[[#This Row],[fecha]], "mmmm") -> julio | F28: ="T"&ROUNDUP(Tabla2[[#This Row],[mes]]/3,0) -> T3 | G28: P019 | H28: Champú reparador | I28: =IF(Tabla2[[#This Row],[precio_unitario]]<=30,"Económico",IF(Tabla2[[#This Row],[precio_unitario]]<=58.49,"Accesible","Caro")) -> Caro | J28: Perfumería y Belleza | K28: 1 | L28: 63.62 | M28: 34.15 | N28: 0 | O28: =K28*L28*(1-N28) -> 63.62 | P28: =M28*K28 -> 34.15 | Q28: =O28-P28 -> 29.47 | R28: =IFERROR(Q28/O28,0) -> 0.46321911 | S28: Cataluña | T28: online
A29: V00035 | B29: 45664 | C29: =YEAR(Tabla2[[#This Row],[fecha]]) -> 2025 | D29: =MONTH(Tabla2[[#This Row],[fecha]]) -> 1 | E29: =TEXT(Tabla2[[#This Row],[fecha]], "mmmm") -> enero | F29: ="T"&ROUNDUP(Tabla2[[#This Row],[mes]]/3,0) -> T1 | G29: P007 | H29: Aspiradora sin cable | I29: =IF(Tabla2[[#This Row],[precio_unitario]]<=30,"Económico",IF(Tabla2[[#This Row],[precio_unitario]]<=58.49,"Accesible","Caro")) -> Económico | J29: Hogar | K29: 4 | L29: 21.12 | M29: 12.91 | N29: 0 | O29: =K29*L29*(1-N29) -> 84.48 | P29: =M29*K29 -> 51.64 | Q29: =O29-P29 -> 32.84 | R29: =IFERROR(Q29/O29,0) -> 0.38873106 | S29: C. Valenciana | T29: tienda_fisica
A30: V01396 | B30: 45857 | C30: =YEAR(Tabla2[[#This Row],[fecha]]) -> 2025 | D30: =MONTH(Tabla2[[#This Row],[fecha]]) -> 7 | E30: =TEXT(Tabla2[[#This Row],[fecha]], "mmmm") -> julio | F30: ="T"&ROUNDUP(Tabla2[[#This Row],[mes]]/3,0) -> T3 | G30: P011 | H30: Café en grano 1kg | I30: =IF(Tabla2[[#This Row],[precio_unitario]]<=30,"Económico",IF(Tabla2[[#This Row],[precio_unitario]]<=58.49,"Accesible","Caro")) -> Económico | J30: Alimentación | K30: 1 | L30: 20.9 | M30: 11.03 | N30: 0 | O30: =K30*L30*(1-N30) -> 20.9 | P30: =M30*K30 -> 11.03 | Q30: =O30-P30 -> 9.87 | R30: =IFERROR(Q30/O30,0) -> 0.4722488 | S30: C. Valenciana | T30: online
A31: V01023 | B31: 46003 | C31: =YEAR(Tabla2[[#This Row],[fecha]]) -> 2025 | D31: =MONTH(Tabla2[[#This Row],[fecha]]) -> 12 | E31: =TEXT(Tabla2[[#This Row],[fecha]], "mmmm") -> diciembre | F31: ="T"&ROUNDUP(Tabla2[[#This Row],[mes]]/3,0) -> T4 | G31: P007 | H31: Aspiradora sin cable | I31: =IF(Tabla2[[#This Row],[precio_unitario]]<=30,"Económico",IF(Tabla2[[#This Row],[precio_unitario]]<=58.49,"Accesible","Caro")) -> Económico | J31: Hogar | K31: 1 | L31: 18.86 | M31: 12.39 | N31: 0.2 | O31: =K31*L31*(1-N31) -> 15.088 | P31: =M31*K31 -> 12.39 | Q31: =O31-P31 -> 2.698 | R31: =IFERROR(Q31/O31,0) -> 0.1788176 | S31: Cataluña | T31: tienda_fisica
A32: V00197 | B32: 45729 | C32: =YEAR(Tabla2[[#This Row],[fecha]]) -> 2025 | D32: =MONTH(Tabla2[[#This Row],[fecha]]) -> 3 | E32: =TEXT(Tabla2[[#This Row],[fecha]], "mmmm") -> marzo | F32: ="T"&ROUNDUP(Tabla2[[#This Row],[mes]]/3,0) -> T1 | G32: P013 | H32: Camiseta básica algodón | I32: =IF(Tabla2[[#This Row],[precio_unitario]]<=30,"Económico",IF(Tabla2[[#This Row],[precio_unitario]]<=58.49,"Accesible","Caro")) -> Caro | J32: Moda | K32: 4 | L32: 72.39 | M32: 46.78 | N32: 0 | O32: =K32*L32*(1-N32) -> 289.56 | P32: =M32*K32 -> 187.12 | Q32: =O32-P32 -> 102.44 | R32: =IFERROR(Q32/O32,0) -> 0.35377815 | S32: C. Valenciana | T32: online
A33: V00413 | B33: 45848 | C33: =YEAR(Tabla2[[#This Row],[fecha]]) -> 2025 | D33: =MONTH(Tabla2[[#This Row],[fecha]]) -> 7 | E33: =TEXT(Tabla2[[#This Row],[fecha]], "mmmm") -> julio | F33: ="T"&ROUNDUP(Tabla2[[#This Row],[mes]]/3,0) -> T3 | G33: P009 | H33: Aceite de oliva virgen extra 1L | I33: =IF(Tabla2[[#This Row],[precio_unitario]]<=30,"Económico",IF(Tabla2[[#This Row],[precio_unitario]]<=58.49,"Accesible","Caro")) -> Económico | J33: Alimentación | K33: 4 | L33: 7.71 | M33: 4.49 | N33: 0 | O33: =K33*L33*(1-N33) -> 30.84 | P33: =M33*K33 -> 17.96 | Q33: =O33-P33 -> 12.88 | R33: =IFERROR(Q33/O33,0) -> 0.41763943 | S33: Aragón | T33: tienda_fisica
... A45: V00195 | B45: 45597 | C45: =YEAR(Tabla2[[#This Row],[fecha]]) -> 2024 | D45: =MONTH(Tabla2[[#This Row],[fecha]]) -> 11 | E45: =TEXT(Tabla2[[#This Row],[fecha]], "mmmm") -> noviembre | F45: ="T"&ROUNDUP(Tabla2[[#This Row],[mes]]/3,0) -> T4 | G45: P001 | H45: Auriculares inalámbricos | I45: =IF(Tabla2[[#This Row],[precio_unitario]]<=30,"Económico",IF(Tabla2[[#This Row],[precio_unitario]]<=58.49,"Accesible","Caro")) -> Caro | J45: Electrónica | K45: 3 | L45: 129.05 | M45: 84.04 | N45: 0.08 | O45: =K45*L45*(1-N45) -> 356.178 | P45: =M45*K45 -> 252.12 | Q45: =O45-P45 -> 104.058 | R45: =IFERROR(Q45/O45,0) -> 0.29215168 | S45: Madrid | T45: online
A46: V00906 | B46: 45461 | C46: =YEAR(Tabla2[[#This Row],[fecha]]) -> 2024 | D46: =MONTH(Tabla2[[#This Row],[fecha]]) -> 6 | E46: =TEXT(Tabla2[[#This Row],[fecha]], "mmmm") -> junio | F46: ="T"&ROUNDUP(Tabla2[[#This Row],[mes]]/3,0) -> T2 | G46: P003 | H46: Tablet 10" | I46: =IF(Tabla2[[#This Row],[precio_unitario]]<=30,"Económico",IF(Tabla2[[#This Row],[precio_unitario]]<=58.49,"Accesible","Caro")) -> Caro | J46: Electrónica | K46: 1 | L46: =INDEX(Tabla3[precio_venta_recomendado], MATCH(Tabla2[[#This Row],[id_producto]], Tabla3[id_producto], 0)) -> 177.72 | M46: 89.58 | N46: 0 | O46: =K46*L46*(1-N46) -> 177.72 | P46: =M46*K46 -> 89.58 | Q46: =O46-P46 -> 88.14 | R46: =IFERROR(Q46/O46,0) -> 0.49594868 | S46: Madrid | T46: online
A47: V00825 | B47: 45692 | C47: =YEAR(Tabla2[[#This Row],[fecha]]) -> 2025 | D47: =MONTH(Tabla2[[#This Row],[fecha]]) -> 2 | E47: =TEXT(Tabla2[[#This Row],[fecha]], "mmmm") -> febrero | F47: ="T"&ROUNDUP(Tabla2[[#This Row],[mes]]/3,0) -> T1 | G47: P010 | H47: Cava brut nature | I47: =IF(Tabla2[[#This Row],[precio_unitario]]<=30,"Económico",IF(Tabla2[[#This Row],[precio_unitario]]<=58.49,"Accesible","Caro")) -> Económico | J47: Alimentación | K47: 1 | L47: 17.39 | M47: 11.71 | N47: 0 | O47: =K47*L47*(1-N47) -> 17.39 | P47: =M47*K47 -> 11.71 | Q47: =O47-P47 -> 5.68 | R47: =IFERROR(Q47/O47,0) -> 0.3266245 | S47: Madrid | T47: tienda_fisica
A48: V01956 | B48: 45361 | C48: =YEAR(Tabla2[[#This Row],[fecha]]) -> 2024 | D48: =MONTH(Tabla2[[#This Row],[fecha]]) -> 3 | E48: =TEXT(Tabla2[[#This Row],[fecha]], "mmmm") -> marzo | F48: ="T"&ROUNDUP(Tabla2[[#This Row],[mes]]/3,0) -> T1 | G48: P015 | H48: Zapatillas running | I48: =IF(Tabla2[[#This Row],[precio_unitario]]<=30,"Económico",IF(Tabla2[[#This Row],[precio_unitario]]<=58.49,"Accesible","Caro")) -> Caro | J48: Moda | K48: 7 | L48: 82.99 | M48: 40.72 | N48: 0 | O48: =K48*L48*(1-N48) -> 580.93 | P48: =M48*K48 -> 285.04 | Q48: =O48-P48 -> 295.89 | R48: =IFERROR(Q48/O48,0) -> 0.50933847 | S48: Andalucía | T48: tienda_fisica
A49: V01982 | B49: 45945 | C49: =YEAR(Tabla2[[#This Row],[fecha]]) -> 2025 | D49: =MONTH(Tabla2[[#This Row],[fecha]]) -> 10 | E49: =TEXT(Tabla2[[#This Row],[fecha]], "mmmm") -> octubre | F49: ="T"&ROUNDUP(Tabla2[[#This Row],[mes]]/3,0) -> T4 | G49: P015 | H49: Zapatillas running | I49: =IF(Tabla2[[#This Row],[precio_unitario]]<=30,"Económico",IF(Tabla2[[#This Row],[precio_unitario]]<=58.49,"Accesible","Caro")) -> Caro | J49: Moda | K49: 2 | L49: 80.75 | M49: 42.31 | N49: 0 | O49: =K49*L49*(1-N49) -> 161.5 | P49: =M49*K49 -> 84.62 | Q49: =O49-P49 -> 76.88 | R49: =IFERROR(Q49/O49,0) -> 0.47603715 | S49: C. Valenciana | T49: online
A50: V00260 | B50: 45809 | C50: =YEAR(Tabla2[[#This Row],[fecha]]) -> 2025 | D50: =MONTH(Tabla2[[#This Row],[fecha]]) -> 6 | E50: =TEXT(Tabla2[[#This Row],[fecha]], "mmmm") -> junio | F50: ="T"&ROUNDUP(Tabla2[[#This Row],[mes]]/3,0) -> T2 | G50: P018 | H50: Crema facial hidratante | I50: =IF(Tabla2[[#This Row],[precio_unitario]]<=30,"Económico",IF(Tabla2[[#This Row],[precio_unitario]]<=58.49,"Accesible","Caro")) -> Accesible | J50: Perfumería y Belleza | K50: 3 | L50: 30.63 | M50: 16.73 | N50: 0 | O50: =K50*L50*(1-N50) -> 91.89 | P50: =M50*K50 -> 50.19 | Q50: =O50-P50 -> 41.7 | R50: =IFERROR(Q50/O50,0) -> 0.45380346 | S50: Madrid | T50: online
A51: V01404 | B51: 45841 | C51: =YEAR(Tabla2[[#This Row],[fecha]]) -> 2025 | D51: =MONTH(Tabla2[[#This Row],[fecha]]) -> 7 | E51: =TEXT(Tabla2[[#This Row],[fecha]], "mmmm") -> julio | F51: ="T"&ROUNDUP(Tabla2[[#This Row],[mes]]/3,0) -> T3 | G51: P005 | H51: Robot de cocina | I51: =IF(Tabla2[[#This Row],[precio_unitario]]<=30,"Económico",IF(Tabla2[[#This Row],[precio_unitario]]<=58.49,"Accesible","Caro")) -> Accesible | J51: Hogar | K51: 4 | L51: 58.47 | M51: 40.71 | N51: 0 | O51: =K51*L51*(1-N51) -> 233.88 | P51: =M51*K51 -> 162.84 | Q51: =O51-P51 -> 71.04 | R51: =IFERROR(Q51/O51,0) -> 0.30374551 | S51: Cataluña | T51: tienda_fisica
A52: V01299 | B52: 45946 | C52: =YEAR(Tabla2[[#This Row],[fecha]]) -> 2025 | D52: =MONTH(Tabla2[[#This Row],[fecha]]) -> 10 | E52: =TEXT(Tabla2[[#This Row],[fecha]], "mmmm") -> octubre | F52: ="T"&ROUNDUP(Tabla2[[#This Row],[mes]]/3,0) -> T4 | G52: P003 | H52: Tablet 10" | I52: =IF(Tabla2[[#This Row],[precio_unitario]]<=30,"Económico",IF(Tabla2[[#This Row],[precio_unitario]]<=58.49,"Accesible","Caro")) -> Caro | J52: Electrónica | K52: 4 | L52: 169.25 | M52: 97.54 | N52: 0 | O52: =K52*L52*(1-N52) -> 677 | P52: =M52*K52 -> 390.16 | Q52: =O52-P52 -> 286.84 | R52: =IFERROR(Q52/O52,0) -> 0.42369276 | S52: C. Valenciana | T52: tienda_fisica
A53: V01552 | B53: 45566 | C53: =YEAR(Tabla2[[#This Row],[fecha]]) -> 2024 | D53: =MONTH(Tabla2[[#This Row],[fecha]]) -> 10 | E53: =TEXT(Tabla2[[#This Row],[fecha]], "mmmm") -> octubre | F53: ="T"&ROUNDUP(Tabla2[[#This Row],[mes]]/3,0) -> T4 | G53: P004 | H53: Altavoz Bluetooth | I53: =IF(Tabla2[[#This Row],[precio_unitario]]<=30,"Económico",IF(Tabla2[[#This Row],[precio_unitario]]<=58.49,"Accesible","Caro")) -> Caro | J53: Electrónica | K53: 5 | L53: 165.91 | M53: 113.32 | N53: 0 | O53: =K53*L53*(1-N53) -> 829.55 | P53: =M53*K53 -> 566.6 | Q53: =O53-P53 -> 262.95 | R53: =IFERROR(Q53/O53,0) -> 0.31697909 | S53: Baleares | T53: tienda_fisica
A54: V01672 | B54: 45582 | C54: =YEAR(Tabla2[[#This Row],[fecha]]) -> 2024 | D54: =MONTH(Tabla2[[#This Row],[fecha]]) -> 10 | E54: =TEXT(Tabla2[[#This Row],[fecha]], "mmmm") -> octubre | F54: ="T"&ROUNDUP(Tabla2[[#This Row],[mes]]/3,0) -> T4 | G54: P004 | H54: Altavoz Bluetooth | I54: =IF(Tabla2[[#This Row],[precio_unitario]]<=30,"Económico",IF(Tabla2[[#This Row],[precio_unitario]]<=58.49,"Accesible","Caro")) -> Caro | J54: Electrónica | K54: 1 | L54: 160.69 | M54: 111.3 | N54: 0 | O54: =K54*L54*(1-N54) -> 160.69 | P54: =M54*K54 -> 111.3 | Q54: =O54-P54 -> 49.39 | R54: =IFERROR(Q54/O54,0) -> 0.307362 | S54: Andalucía | T54: tienda_fisica
A55: V00596 | B55: 45338 | C55: =YEAR(Tabla2[[#This Row],[fecha]]) -> 2024 | D55: =MONTH(Tabla2[[#This Row],[fecha]]) -> 2 | E55: =TEXT(Tabla2[[#This Row],[fecha]], "mmmm") -> febrero | F55: ="T"&ROUNDUP(Tabla2[[#This Row],[mes]]/3,0) -> T1 | G55: P020 | H55: Set de maquillaje | I55: =IF(Tabla2[[#This Row],[precio_unitario]]<=30,"Económico",IF(Tabla2[[#This Row],[precio_unitario]]<=58.49,"Accesible","Caro")) -> Caro | J55: Perfumería y Belleza | K55: 1 | L55: 64.23 | M55: 34.86 | N55: 0.2 | O55: =K55*L55*(1-N55) -> 51.384 | P55: =M55*K55 -> 34.86 | Q55: =O55-P55 -> 16.524 | R55: =IFERROR(Q55/O55,0) -> 0.3215787 | S55: Cataluña | T55: tienda_fisica
A56: V01438 | B56: 45942 | C56: =YEAR(Tabla2[[#This Row],[fecha]]) -> 2025 | D56: =MONTH(Tabla2[[#This Row],[fecha]]) -> 10 | E56: =TEXT(Tabla2[[#This Row],[fecha]], "mmmm") -> octubre | F56: ="T"&ROUNDUP(Tabla2[[#This Row],[mes]]/3,0) -> T4 | G56: P012 | H56: Chocolate a la taza 500g | I56: =IF(Tabla2[[#This Row],[precio_unitario]]<=30,"Económico",IF(Tabla2[[#This Row],[precio_unitario]]<=58.49,"Accesible","Caro")) -> Económico | J56: Alimentación | K56: 1 | L56: 9.02 | M56: 5.52 | N56: 0.27 | O56: =K56*L56*(1-N56) -> 6.5846 | P56: =M56*K56 -> 5.52 | Q56: =O56-P56 -> 1.0646 | R56: =IFERROR(Q56/O56,0) -> 0.16168028 | S56: C. Valenciana | T56: online
A57: V00766 | B57: 45439 | C57: =YEAR(Tabla2[[#This Row],[fecha]]) -> 2024 | D57: =MONTH(Tabla2[[#This Row],[fecha]]) -> 5 | E57: =TEXT(Tabla2[[#This Row],[fecha]], "mmmm") -> mayo | F57: ="T"&ROUNDUP(Tabla2[[#This Row],[mes]]/3,0) -> T2 | G57: P010 | H57: Cava brut nature | I57: =IF(Tabla2[[#This Row],[precio_unitario]]<=30,"Económico",IF(Tabla2[[#This Row],[precio_unitario]]<=58.49,"Accesible","Caro")) -> Económico | J57: Alimentación | K57: 1 | L57: 16.81 | M57: 10.94 | N57: 0 | O57: =K57*L57*(1-N57) -> 16.81 | P57: =M57*K57 -> 10.94 | Q57: =O57-P57 -> 5.87 | R57: =IFERROR(Q57/O57,0) -> 0.34919691 | S57: Cataluña | T57: tienda_fisica
A58: V00508 | B58: 46018 | C58: =YEAR(Tabla2[[#This Row],[fecha]]) -> 2025 | D58: =MONTH(Tabla2[[#This Row],[fecha]]) -> 12 | E58: =TEXT(Tabla2[[#This Row],[fecha]], "mmmm") -> diciembre | F58: ="T"&ROUNDUP(Tabla2[[#This Row],[mes]]/3,0) -> T4 | G58: P017 | H58: Perfume eau de parfum 90ml | I58: =IF(Tabla2[[#This Row],[precio_unitario]]<=30,"Económico",IF(Tabla2[[#This Row],[precio_unitario]]<=58.49,"Accesible","Caro")) -> Accesible | J58: Perfumería y Belleza | K58: 1 | L58: 49 | M58: 23.66 | N58: 0.11 | O58: =K58*L58*(1-N58) -> 43.61 | P58: =M58*K58 -> 23.66 | Q58: =O58-P58 -> 19.95 | R58: =IFERROR(Q58/O58,0) -> 0.45746388 | S58: Cataluña | T58: online
... A63: V01593 | B63: 45315 | C63: =YEAR(Tabla2[[#This Row],[fecha]]) -> 2024 | D63: =MONTH(Tabla2[[#This Row],[fecha]]) -> 1 | E63: =TEXT(Tabla2[[#This Row],[fecha]], "mmmm") -> enero | F63: ="T"&ROUNDUP(Tabla2[[#This Row],[mes]]/3,0) -> T1 | G63: P017 | H63: Perfume eau de parfum 90ml | I63: =IF(Tabla2[[#This Row],[precio_unitario]]<=30,"Económico",IF(Tabla2[[#This Row],[precio_unitario]]<=58.49,"Accesible","Caro")) -> Accesible | J63: Perfumería y Belleza | K63: 2 | L63: 49.34 | M63: 21.96 | N63: 0 | O63: =K63*L63*(1-N63) -> 98.68 | P63: =M63*K63 -> 43.92 | Q63: =O63-P63 -> 54.76 | R63: =IFERROR(Q63/O63,0) -> 0.55492501 | S63: Baleares | T63: tienda_fisica
A64: V02040 | B64: 45843 | C64: =YEAR(Tabla2[[#This Row],[fecha]]) -> 2025 | D64: =MONTH(Tabla2[[#This Row],[fecha]]) -> 7 | E64: =TEXT(Tabla2[[#This Row],[fecha]], "mmmm") -> julio | F64: ="T"&ROUNDUP(Tabla2[[#This Row],[mes]]/3,0) -> T3 | G64: P015 | H64: Zapatillas running | I64: =IF(Tabla2[[#This Row],[precio_unitario]]<=30,"Económico",IF(Tabla2[[#This Row],[precio_unitario]]<=58.49,"Accesible","Caro")) -> Caro | J64: Moda | K64: 8 | L64: 81.78 | M64: =INDEX(Tabla3[coste_objetivo], MATCH(Tabla2[[#This Row],[id_producto]], Tabla3[id_producto],0)) -> 42.79 | N64: 0 | O64: =K64*L64*(1-N64) -> 654.24 | P64: =M64*K64 -> 342.32 | Q64: =O64-P64 -> 311.92 | R64: =IFERROR(Q64/O64,0) -> 0.47676694 | S64: Madrid | T64: tienda_fisica
A65: V00205 | B65: 45515 | C65: =YEAR(Tabla2[[#This Row],[fecha]]) -> 2024 | D65: =MONTH(Tabla2[[#This Row],[fecha]]) -> 8 | E65: =TEXT(Tabla2[[#This Row],[fecha]], "mmmm") -> agosto | F65: ="T"&ROUNDUP(Tabla2[[#This Row],[mes]]/3,0) -> T3 | G65: P001 | H65: Auriculares inalámbricos | I65: =IF(Tabla2[[#This Row],[precio_unitario]]<=30,"Económico",IF(Tabla2[[#This Row],[precio_unitario]]<=58.49,"Accesible","Caro")) -> Caro | J65: Electrónica | K65: 2 | L65: 131.85 | M65: 87.97 | N65: 0.28 | O65: =K65*L65*(1-N65) -> 189.864 | P65: =M65*K65 -> 175.94 | Q65: =O65-P65 -> 13.924 | R65: =IFERROR(Q65/O65,0) -> 0.073336704 | S65: Madrid | T65: online
A66: V00396 | B66: 45925 | C66: =YEAR(Tabla2[[#This Row],[fecha]]) -> 2025 | D66: =MONTH(Tabla2[[#This Row],[fecha]]) -> 9 | E66: =TEXT(Tabla2[[#This Row],[fecha]], "mmmm") -> septiembre | F66: ="T"&ROUNDUP(Tabla2[[#This Row],[mes]]/3,0) -> T3 | G66: P007 | H66: Aspiradora sin cable | I66: =IF(Tabla2[[#This Row],[precio_unitario]]<=30,"Económico",IF(Tabla2[[#This Row],[precio_unitario]]<=58.49,"Accesible","Caro")) -> Económico | J66: Hogar | K66: 7 | L66: 18.29 | M66: 13.12 | N66: 0 | O66: =K66*L66*(1-N66) -> 128.03 | P66: =M66*K66 -> 91.84 | Q66: =O66-P66 -> 36.19 | R66: =IFERROR(Q66/O66,0) -> 0.28266812 | S66: C. Valenciana | T66: tienda_fisica
A67: V00747 | B67: 46006 | C67: =YEAR(Tabla2[[#This Row],[fecha]]) -> 2025 | D67: =MONTH(Tabla2[[#This Row],[fecha]]) -> 12 | E67: =TEXT(Tabla2[[#This Row],[fecha]], "mmmm") -> diciembre | F67: ="T"&ROUNDUP(Tabla2[[#This Row],[mes]]/3,0) -> T4 | G67: P015 | H67: Zapatillas running | I67: =IF(Tabla2[[#This Row],[precio_unitario]]<=30,"Económico",IF(Tabla2[[#This Row],[precio_unitario]]<=58.49,"Accesible","Caro")) -> Caro | J67: Moda | K67: 4 | L67: 82.54 | M67: 41.01 | N67: 0 | O67: =K67*L67*(1-N67) -> 330.16 | P67: =M67*K67 -> 164.04 | Q67: =O67-P67 -> 166.12 | R67: =IFERROR(Q67/O67,0) -> 0.50314999 | S67: Cataluña | T67: tienda_fisica
A68: V00052 | B68: 45912 | C68: =YEAR(Tabla2[[#This Row],[fecha]]) -> 2025 | D68: =MONTH(Tabla2[[#This Row],[fecha]]) -> 9 | E68: =TEXT(Tabla2[[#This Row],[fecha]], "mmmm") -> septiembre | F68: ="T"&ROUNDUP(Tabla2[[#This Row],[mes]]/3,0) -> T3 | G68: P006 | H68: Set de sartenes | I68: =IF(Tabla2[[#This Row],[precio_unitario]]<=30,"Económico",IF(Tabla2[[#This Row],[precio_unitario]]<=58.49,"Accesible","Caro")) -> Accesible | J68: Hogar | K68: 1 | L68: 50.19 | M68: 25.59 | N68: 0.13 | O68: =K68*L68*(1-N68) -> 43.6653 | P68: =M68*K68 -> 25.59 | Q68: =O68-P68 -> 18.0753 | R68: =IFERROR(Q68/O68,0) -> 0.41395112 | S68: Madrid | T68: tienda_fisica
A69: V01887 | B69: 45694 | C69: =YEAR(Tabla2[[#This Row],[fecha]]) -> 2025 | D69: =MONTH(Tabla2[[#This Row],[fecha]]) -> 2 | E69: =TEXT(Tabla2[[#This Row],[fecha]], "mmmm") -> febrero | F69: ="T"&ROUNDUP(Tabla2[[#This Row],[mes]]/3,0) -> T1 | G69: P009 | H69: Aceite de oliva virgen extra 1L | I69: =IF(Tabla2[[#This Row],[precio_unitario]]<=30,"Económico",IF(Tabla2[[#This Row],[precio_unitario]]<=58.49,"Accesible","Caro")) -> Económico | J69: Alimentación | K69: 6 | L69: 8.24 | M69: 4.29 | N69: 0 | O69: =K69*L69*(1-N69) -> 49.44 | P69: =M69*K69 -> 25.74 | Q69: =O69-P69 -> 23.7 | R69: =IFERROR(Q69/O69,0) -> 0.47936893 | S69: C. Valenciana | T69: tienda_fisica
A70: V01757 | B70: 45641 | C70: =YEAR(Tabla2[[#This Row],[fecha]]) -> 2024 | D70: =MONTH(Tabla2[[#This Row],[fecha]]) -> 12 | E70: =TEXT(Tabla2[[#This Row],[fecha]], "mmmm") -> diciembre | F70: ="T"&ROUNDUP(Tabla2[[#This Row],[mes]]/3,0) -> T4 | G70: P001 | H70: Auriculares inalámbricos | I70: =IF(Tabla2[[#This Row],[precio_unitario]]<=30,"Económico",IF(Tabla2[[#This Row],[precio_unitario]]<=58.49,"Accesible","Caro")) -> Caro | J70: Electrónica | K70: 3 | L70: 127.66 | M70: 86 | N70: 0 | O70: =K70*L70*(1-N70) -> 382.98 | P70: =M70*K70 -> 258 | Q70: =O70-P70 -> 124.98 | R70: =IFERROR(Q70/O70,0) -> 0.32633558 | S70: Cataluña | T70: online
A71: V01057 | B71: 45783 | C71: =YEAR(Tabla2[[#This Row],[fecha]]) -> 2025 | D71: =MONTH(Tabla2[[#This Row],[fecha]]) -> 5 | E71: =TEXT(Tabla2[[#This Row],[fecha]], "mmmm") -> mayo | F71: ="T"&ROUNDUP(Tabla2[[#This Row],[mes]]/3,0) -> T2 | G71: P016 | H71: Bolso bandolera | I71: =IF(Tabla2[[#This Row],[precio_unitario]]<=30,"Económico",IF(Tabla2[[#This Row],[precio_unitario]]<=58.49,"Accesible","Caro")) -> Caro | J71: Moda | K71: 4 | L71: 81.36 | M71: 39.4 | N71: 0 | O71: =K71*L71*(1-N71) -> 325.44 | P71: =M71*K71 -> 157.6 | Q71: =O71-P71 -> 167.84 | R71: =IFERROR(Q71/O71,0) -> 0.51573255 | S71: Cataluña | T71: tienda_fisica
A72: V01907 | B72: 45682 | C72: =YEAR(Tabla2[[#This Row],[fecha]]) -> 2025 | D72: =MONTH(Tabla2[[#This Row],[fecha]]) -> 1 | E72: =TEXT(Tabla2[[#This Row],[fecha]], "mmmm") -> enero | F72: ="T"&ROUNDUP(Tabla2[[#This Row],[mes]]/3,0) -> T1 | G72: P007 | H72: Aspiradora sin cable | I72: =IF(Tabla2[[#This Row],[precio_unitario]]<=30,"Económico",IF(Tabla2[[#This Row],[precio_unitario]]<=58.49,"Accesible","Caro")) -> Económico | J72: Hogar | K72: 1 | L72: 19.39 | M72: 13.35 | N72: 0 | O72: =K72*L72*(1-N72) -> 19.39 | P72: =M72*K72 -> 13.35 | Q72: =O72-P72 -> 6.04 | R72: =IFERROR(Q72/O72,0) -> 0.31150077 | S72: Cataluña | T72: online
A73: V01454 | B73: 45501 | C73: =YEAR(Tabla2[[#This Row],[fecha]]) -> 2024 | D73: =MONTH(Tabla2[[#This Row],[fecha]]) -> 7 | E73: =TEXT(Tabla2[[#This Row],[fecha]], "mmmm") -> julio | F73: ="T"&ROUNDUP(Tabla2[[#This Row],[mes]]/3,0) -> T3 | G73: P011 | H73: Café en grano 1kg | I73: =IF(Tabla2[[#This Row],[precio_unitario]]<=30,"Económico",IF(Tabla2[[#This Row],[precio_unitario]]<=58.49,"Accesible","Caro")) -> Económico | J73: Alimentación | K73: 1 | L73: 22.8 | M73: 11.56 | N73: 0.25 | O73: =K73*L73*(1-N73) -> 17.1 | P73: =M73*K73 -> 11.56 | Q73: =O73-P73 -> 5.54 | R73: =IFERROR(Q73/O73,0) -> 0.32397661 | S73: Baleares | T73: tienda_fisica
A74: V00329 | B74: 45878 | C74: =YEAR(Tabla2[[#This Row],[fecha]]) -> 2025 | D74: =MONTH(Tabla2[[#This Row],[fecha]]) -> 8 | E74: =TEXT(Tabla2[[#This Row],[fecha]], "mmmm") -> agosto | F74: ="T"&ROUNDUP(Tabla2[[#This Row],[mes]]/3,0) -> T3 | G74: P016 | H74: Bolso bandolera | I74: =IF(Tabla2[[#This Row],[precio_unitario]]<=30,"Económico",IF(Tabla2[[#This Row],[precio_unitario]]<=58.49,"Accesible","Caro")) -> Caro | J74: Moda | K74: 1 | L74: 81.57 | M74: 41.02 | N74: 0 | O74: =K74*L74*(1-N74) -> 81.57 | P74: =M74*K74 -> 41.02 | Q74: =O74-P74 -> 40.55 | R74: =IFERROR(Q74/O74,0) -> 0.49711904 | S74: Aragón | T74: tienda_fisica
A75: V01930 | B75: 45620 | C75: =YEAR(Tabla2[[#This Row],[fecha]]) -> 2024 | D75: =MONTH(Tabla2[[#This Row],[fecha]]) -> 11 | E75: =TEXT(Tabla2[[#This Row],[fecha]], "mmmm") -> noviembre | F75: ="T"&ROUNDUP(Tabla2[[#This Row],[mes]]/3,0) -> T4 | G75: P008 | H75: Lámpara LED de pie | I75: =IF(Tabla2[[#This Row],[precio_unitario]]<=30,"Económico",IF(Tabla2[[#This Row],[precio_unitario]]<=58.49,"Accesible","Caro")) -> Caro | J75: Hogar | K75: 3 | L75: 97.35 | M75: 56.61 | N75: 0.09 | O75: =K75*L75*(1-N75) -> 265.7655 | P75: =M75*K75 -> 169.83 | Q75: =O75-P75 -> 95.9355 | R75: =IFERROR(Q75/O75,0) -> 0.36097801 | S75: Cataluña | T75: tienda_fisica
A76: V00716 | B76: 45415 | C76: =YEAR(Tabla2[[#This Row],[fecha]]) -> 2024 | D76: =MONTH(Tabla2[[#This Row],[fecha]]) -> 5 | E76: =TEXT(Tabla2[[#This Row],[fecha]], "mmmm") -> mayo | F76: ="T"&ROUNDUP(Tabla2[[#This Row],[mes]]/3,0) -> T2 | G76: P005 | H76: Robot de cocina | I76: =IF(Tabla2[[#This Row],[precio_unitario]]<=30,"Económico",IF(Tabla2[[#This Row],[precio_unitario]]<=58.49,"Accesible","Caro")) -> Caro | J76: Hogar | K76: 5 | L76: 63.52 | M76: 41.6 | N76: 0 | O76: =K76*L76*(1-N76) -> 317.6 | P76: =M76*K76 -> 208 | Q76: =O76-P76 -> 109.6 | R76: =IFERROR(Q76/O76,0) -> 0.34508816 | S76: Cataluña | T76: tienda_fisica
... A183: V01468 | B183: 45680 | C183: =YEAR(Tabla2[[#This Row],[fecha]]) -> 2025 | D183: =MONTH(Tabla2[[#This Row],[fecha]]) -> 1 | E183: =TEXT(Tabla2[[#This Row],[fecha]], "mmmm") -> enero | F183: ="T"&ROUNDUP(Tabla2[[#This Row],[mes]]/3,0) -> T1 | G183: P008 | H183: Lámpara LED de pie | I183: =IF(Tabla2[[#This Row],[precio_unitario]]<=30,"Económico",IF(Tabla2[[#This Row],[precio_unitario]]<=58.49,"Accesible","Caro")) -> Caro | J183: Hogar | K183: 1 | L183: 98.42 | M183: 58.61 | N183: 0 | O183: =K183*L183*(1-N183) -> 98.42 | P183: =M183*K183 -> 58.61 | Q183: =O183-P183 -> 39.81 | R183: =IFERROR(Q183/O183,0) -> 0.40449096 | S183: Madrid | T183: tienda_fisica
A184: V00340 | B184: 45473 | C184: =YEAR(Tabla2[[#This Row],[fecha]]) -> 2024 | D184: =MONTH(Tabla2[[#This Row],[fecha]]) -> 6 | E184: =TEXT(Tabla2[[#This Row],[fecha]], "mmmm") -> junio | F184: ="T"&ROUNDUP(Tabla2[[#This Row],[mes]]/3,0) -> T2 | G184: P015 | H184: Zapatillas running | I184: =IF(Tabla2[[#This Row],[precio_unitario]]<=30,"Económico",IF(Tabla2[[#This Row],[precio_unitario]]<=58.49,"Accesible","Caro")) -> Caro | J184: Moda | K184: 3 | L184: 82 | M184: =INDEX(Tabla3[coste_objetivo], MATCH(Tabla2[[#This Row],[id_producto]], Tabla3[id_producto],0)) -> 42.79 | N184: 0 | O184: =K184*L184*(1-N184) -> 246 | P184: =M184*K184 -> 128.37 | Q184: =O184-P184 -> 117.63 | R184: =IFERROR(Q184/O184,0) -> 0.47817073 | S184: Andalucía | T184: tienda_fisica
A185: V01287 | B185: 45682 | C185: =YEAR(Tabla2[[#This Row],[fecha]]) -> 2025 | D185: =MONTH(Tabla2[[#This Row],[fecha]]) -> 1 | E185: =TEXT(Tabla2[[#This Row],[fecha]], "mmmm") -> enero | F185: ="T"&ROUNDUP(Tabla2[[#This Row],[mes]]/3,0) -> T1 | G185: P002 | H185: Smartwatch | I185: =IF(Tabla2[[#This Row],[precio_unitario]]<=30,"Económico",IF(Tabla2[[#This Row],[precio_unitario]]<=58.49,"Accesible","Caro")) -> Caro | J185: Electrónica | K185: 4 | L185: 69.89 | M185: 48.22 | N185: 0 | O185: =K185*L185*(1-N185) -> 279.56 | P185: =M185*K185 -> 192.88 | Q185: =O185-P185 -> 86.68 | R185: =IFERROR(Q185/O185,0) -> 0.31005866 | S185: Aragón | T185: online
A186: V01756 | B186: 45947 | C186: =YEAR(Tabla2[[#This Row],[fecha]]) -> 2025 | D186: =MONTH(Tabla2[[#This Row],[fecha]]) -> 10 | E186: =TEXT(Tabla2[[#This Row],[fecha]], "mmmm") -> octubre | F186: ="T"&ROUNDUP(Tabla2[[#This Row],[mes]]/3,0) -> T4 | G186: P020 | H186: Set de maquillaje | I186: =IF(Tabla2[[#This Row],[precio_unitario]]<=30,"Económico",IF(Tabla2[[#This Row],[precio_unitario]]<=58.49,"Accesible","Caro")) -> Accesible | J186: Perfumería y Belleza | K186: 9 | L186: 56.54 | M186: 32.81 | N186: 0 | O186: =K186*L186*(1-N186) -> 508.86 | P186: =M186*K186 -> 295.29 | Q186: =O186-P186 -> 213.57 | R186: =IFERROR(Q186/O186,0) -> 0.41970287 | S186: Baleares | T186: tienda_fisica
A187: V01335 | B187: 45906 | C187: =YEAR(Tabla2[[#This Row],[fecha]]) -> 2025 | D187: =MONTH(Tabla2[[#This Row],[fecha]]) -> 9 | E187: =TEXT(Tabla2[[#This Row],[fecha]], "mmmm") -> septiembre | F187: ="T"&ROUNDUP(Tabla2[[#This Row],[mes]]/3,0) -> T3 | G187: P009 | H187: Aceite de oliva virgen extra 1L | I187: =IF(Tabla2[[#This Row],[precio_unitario]]<=30,"Económico",IF(Tabla2[[#This Row],[precio_unitario]]<=58.49,"Accesible","Caro")) -> Económico | J187: Alimentación | K187: 1 | L187: 7.38 | M187: 4.4 | N187: 0.08 | O187: =K187*L187*(1-N187) -> 6.7896 | P187: =M187*K187 -> 4.4 | Q187: =O187-P187 -> 2.3896 | R187: =IFERROR(Q187/O187,0) -> 0.35195004 | S187: Cataluña | T187: tienda_fisica
A188: V00988 | B188: 45847 | C188: =YEAR(Tabla2[[#This Row],[fecha]]) -> 2025 | D188: =MONTH(Tabla2[[#This Row],[fecha]]) -> 7 | E188: =TEXT(Tabla2[[#This Row],[fecha]], "mmmm") -> julio | F188: ="T"&ROUNDUP(Tabla2[[#This Row],[mes]]/3,0) -> T3 | G188: P006 | H188: Set de sartenes | I188: =IF(Tabla2[[#This Row],[precio_unitario]]<=30,"Económico",IF(Tabla2[[#This Row],[precio_unitario]]<=58.49,"Accesible","Caro")) -> Accesible | J188: Hogar | K188: 4 | L188: 47.72 | M188: =INDEX(Tabla3[coste_objetivo], MATCH(Tabla2[[#This Row],[id_producto]], Tabla3[id_producto],0)) -> 26.63 | N188: 0 | O188: =K188*L188*(1-N188) -> 190.88 | P188: =M188*K188 -> 106.52 | Q188: =O188-P188 -> 84.36 | R188: =IFERROR(Q188/O188,0) -> 0.44195306 | S188: C. Valenciana | T188: online
A189: V02252 | B189: 45706 | C189: =YEAR(Tabla2[[#This Row],[fecha]]) -> 2025 | D189: =MONTH(Tabla2[[#This Row],[fecha]]) -> 2 | E189: =TEXT(Tabla2[[#This Row],[fecha]], "mmmm") -> febrero | F189: ="T"&ROUNDUP(Tabla2[[#This Row],[mes]]/3,0) -> T1 | G189: P015 | H189: Zapatillas running | I189: =IF(Tabla2[[#This Row],[precio_unitario]]<=30,"Económico",IF(Tabla2[[#This Row],[precio_unitario]]<=58.49,"Accesible","Caro")) -> Caro | J189: Moda | K189: 1 | L189: 79.66 | M189: 42.57 | N189: 0.24 | O189: =K189*L189*(1-N189) -> 60.5416 | P189: =M189*K189 -> 42.57 | Q189: =O189-P189 -> 17.9716 | R189: =IFERROR(Q189/O189,0) -> 0.29684713 | S189: Baleares | T189: tienda_fisica
A190: V00182 | B190: 45718 | C190: =YEAR(Tabla2[[#This Row],[fecha]]) -> 2025 | D190: =MONTH(Tabla2[[#This Row],[fecha]]) -> 3 | E190: =TEXT(Tabla2[[#This Row],[fecha]], "mmmm") -> marzo | F190: ="T"&ROUNDUP(Tabla2[[#This Row],[mes]]/3,0) -> T1 | G190: P004 | H190: Altavoz Bluetooth | I190: =IF(Tabla2[[#This Row],[precio_unitario]]<=30,"Económico",IF(Tabla2[[#This Row],[precio_unitario]]<=58.49,"Accesible","Caro")) -> Caro | J190: Electrónica | K190: 5 | L190: 149.56 | M190: =INDEX(Tabla3[coste_objetivo], MATCH(Tabla2[[#This Row],[id_producto]], Tabla3[id_producto],0)) -> 110.03 | N190: 0 | O190: =K190*L190*(1-N190) -> 747.8 | P190: =M190*K190 -> 550.15 | Q190: =O190-P190 -> 197.65 | R190: =IFERROR(Q190/O190,0) -> 0.26430864 | S190: Madrid | T190: tienda_fisica
A191: V01784 | B191: 45842 | C191: =YEAR(Tabla2[[#This Row],[fecha]]) -> 2025 | D191: =MONTH(Tabla2[[#This Row],[fecha]]) -> 7 | E191: =TEXT(Tabla2[[#This Row],[fecha]], "mmmm") -> julio | F191: ="T"&ROUNDUP(Tabla2[[#This Row],[mes]]/3,0) -> T3 | G191: P010 | H191: Cava brut nature | I191: =IF(Tabla2[[#This Row],[precio_unitario]]<=30,"Económico",IF(Tabla2[[#This Row],[precio_unitario]]<=58.49,"Accesible","Caro")) -> Económico | J191: Alimentación | K191: 4 | L191: 15.25 | M191: 11.37 | N191: 0 | O191: =K191*L191*(1-N191) -> 61 | P191: =M191*K191 -> 45.48 | Q191: =O191-P191 -> 15.52 | R191: =IFERROR(Q191/O191,0) -> 0.25442623 | S191: Madrid | T191: tienda_fisica
A192: V01344 | B192: 45521 | C192: =YEAR(Tabla2[[#This Row],[fecha]]) -> 2024 | D192: =MONTH(Tabla2[[#This Row],[fecha]]) -> 8 | E192: =TEXT(Tabla2[[#This Row],[fecha]], "mmmm") -> agosto | F192: ="T"&ROUNDUP(Tabla2[[#This Row],[mes]]/3,0) -> T3 | G192: P004 | H192: Altavoz Bluetooth | I192: =IF(Tabla2[[#This Row],[precio_unitario]]<=30,"Económico",IF(Tabla2[[#This Row],[precio_unitario]]<=58.49,"Accesible","Caro")) -> Caro | J192: Electrónica | K192: 3 | L192: 170.2 | M192: 109.77 | N192: 0 | O192: =K192*L192*(1-N192) -> 510.6 | P192: =M192*K192 -> 329.31 | Q192: =O192-P192 -> 181.29 | R192: =IFERROR(Q192/O192,0) -> 0.35505288 | S192: Baleares | T192: online
A193: V00545 | B193: 45804 | C193: =YEAR(Tabla2[[#This Row],[fecha]]) -> 2025 | D193: =MONTH(Tabla2[[#This Row],[fecha]]) -> 5 | E193: =TEXT(Tabla2[[#This Row],[fecha]], "mmmm") -> mayo | F193: ="T"&ROUNDUP(Tabla2[[#This Row],[mes]]/3,0) -> T2 | G193: P016 | H193: Bolso bandolera | I193: =IF(Tabla2[[#This Row],[precio_unitario]]<=30,"Económico",IF(Tabla2[[#This Row],[precio_unitario]]<=58.49,"Accesible","Caro")) -> Caro | J193: Moda | K193: 3 | L193: 76.48 | M193: 40.3 | N193: 0 | O193: =K193*L193*(1-N193) -> 229.44 | P193: =M193*K193 -> 120.9 | Q193: =O193-P193 -> 108.54 | R193: =IFERROR(Q193/O193,0) -> 0.47306485 | S193: Cataluña | T193: online
A194: V01464 | B194: 45885 | C194: =YEAR(Tabla2[[#This Row],[fecha]]) -> 2025 | D194: =MONTH(Tabla2[[#This Row],[fecha]]) -> 8 | E194: =TEXT(Tabla2[[#This Row],[fecha]], "mmmm") -> agosto | F194: ="T"&ROUNDUP(Tabla2[[#This Row],[mes]]/3,0) -> T3 | G194: P014 | H194: Chaqueta acolchada | I194: =IF(Tabla2[[#This Row],[precio_unitario]]<=30,"Económico",IF(Tabla2[[#This Row],[precio_unitario]]<=58.49,"Accesible","Caro")) -> Económico | J194: Moda | K194: 2 | L194: 14.87 | M194: 9.49 | N194: 0 | O194: =K194*L194*(1-N194) -> 29.74 | P194: =M194*K194 -> 18.98 | Q194: =O194-P194 -> 10.76 | R194: =IFERROR(Q194/O194,0) -> 0.36180229 | S194: Aragón | T194: tienda_fisica
A195: V01268 | B195: 45779 | C195: =YEAR(Tabla2[[#This Row],[fecha]]) -> 2025 | D195: =MONTH(Tabla2[[#This Row],[fecha]]) -> 5 | E195: =TEXT(Tabla2[[#This Row],[fecha]], "mmmm") -> mayo | F195: ="T"&ROUNDUP(Tabla2[[#This Row],[mes]]/3,0) -> T2 | G195: P004 | H195: Altavoz Bluetooth | I195: =IF(Tabla2[[#This Row],[precio_unitario]]<=30,"Económico",IF(Tabla2[[#This Row],[precio_unitario]]<=58.49,"Accesible","Caro")) -> Caro | J195: Electrónica | K195: 8 | L195: 148.88 | M195: 109.77 | N195: 0 | O195: =K195*L195*(1-N195) -> 1191.04 | P195: =M195*K195 -> 878.16 | Q195: =O195-P195 -> 312.88 | R195: =IFERROR(Q195/O195,0) -> 0.26269479 | S195: C. Valenciana | T195: online
A196: V00540 | B196: 45630 | C196: =YEAR(Tabla2[[#This Row],[fecha]]) -> 2024 | D196: =MONTH(Tabla2[[#This Row],[fecha]]) -> 12 | E196: =TEXT(Tabla2[[#This Row],[fecha]], "mmmm") -> diciembre | F196: ="T"&ROUNDUP(Tabla2[[#This Row],[mes]]/3,0) -> T4 | G196: P007 | H196: Aspiradora sin cable | I196: =IF(Tabla2[[#This Row],[precio_unitario]]<=30,"Económico",IF(Tabla2[[#This Row],[precio_unitario]]<=58.49,"Accesible","Caro")) -> Económico | J196: Hogar | K196: 3 | L196: 18.37 | M196: 12.43 | N196: 0.17 | O196: =K196*L196*(1-N196) -> 45.7413 | P196: =M196*K196 -> 37.29 | Q196: =O196-P196 -> 8.4513 | R196: =IFERROR(Q196/O196,0) -> 0.184763 | S196: Aragón | T196: tienda_fisica
A197: V00468 | B197: 45739 | C197: =YEAR(Tabla2[[#This Row],[fecha]]) -> 2025 | D197: =MONTH(Tabla2[[#This Row],[fecha]]) -> 3 | E197: =TEXT(Tabla2[[#This Row],[fecha]], "mmmm") -> marzo | F197: ="T"&ROUNDUP(Tabla2[[#This Row],[mes]]/3,0) -> T1 | G197: P018 | H197: Crema facial hidratante | I197: =IF(Tabla2[[#This Row],[precio_unitario]]<=30,"Económico",IF(Tabla2[[#This Row],[precio_unitario]]<=58.49,"Accesible","Caro")) -> Accesible | J197: Perfumería y Belleza | K197: 5 | L197: 30.31 | M197: 16.9 | N197: 0 | O197: =K197*L197*(1-N197) -> 151.55 | P197: =M197*K197 -> 84.5 | Q197: =O197-P197 -> 67.05 | R197: =IFERROR(Q197/O197,0) -> 0.44242824 | S197: C. Valenciana | T197: online
A198: V00685 | B198: 45829 | C198: =YEAR(Tabla2[[#This Row],[fecha]]) -> 2025 | D198: =MONTH(Tabla2[[#This Row],[fecha]]) -> 6 | E198: =TEXT(Tabla2[[#This Row],[fecha]], "mmmm") -> junio | F198: ="T"&ROUNDUP(Tabla2[[#This Row],[mes]]/3,0) -> T2 | G198: P019 | H198: Champú reparador | I198: =IF(Tabla2[[#This Row],[precio_unitario]]<=30,"Económico",IF(Tabla2[[#This Row],[precio_unitario]]<=58.49,"Accesible","Caro")) -> Caro | J198: Perfumería y Belleza | K198: 1 | L198: 62.34 | M198: 32.12 | N198: 0 | O198: =K198*L198*(1-N198) -> 62.34 | P198: =M198*K198 -> 32.12 | Q198: =O198-P198 -> 30.22 | R198: =IFERROR(Q198/O198,0) -> 0.48476099 | S198: Cataluña | T198: tienda_fisica
A199: V00424 | B199: 45513 | C199: =YEAR(Tabla2[[#This Row],[fecha]]) -> 2024 | D199: =MONTH(Tabla2[[#This Row],[fecha]]) -> 8 | E199: =TEXT(Tabla2[[#This Row],[fecha]], "mmmm") -> agosto | F199: ="T"&ROUNDUP(Tabla2[[#This Row],[mes]]/3,0) -> T3 | G199: P003 | H199: Tablet 10" | I199: =IF(Tabla2[[#This Row],[precio_unitario]]<=30,"Económico",IF(Tabla2[[#This Row],[precio_unitario]]<=58.49,"Accesible","Caro")) -> Caro | J199: Electrónica | K199: 8 | L199: =INDEX(Tabla3[precio_venta_recomendado], MATCH(Tabla2[[#This Row],[id_producto]], Tabla3[id_producto], 0)) -> 177.72 | M199: 97.21 | N199: 0.21 | O199: =K199*L199*(1-N199) -> 1123.1904 | P199: =M199*K199 -> 777.68 | Q199: =O199-P199 -> 345.5104 | R199: =IFERROR(Q199/O199,0) -> 0.30761516 | S199: C. Valenciana | T199: tienda_fisica
A200: V00397 | B200: 45928 | C200: =YEAR(Tabla2[[#This Row],[fecha]]) -> 2025 | D200: =MONTH(Tabla2[[#This Row],[fecha]]) -> 9 | E200: =TEXT(Tabla2[[#This Row],[fecha]], "mmmm") -> septiembre | F200: ="T"&ROUNDUP(Tabla2[[#This Row],[mes]]/3,0) -> T3 | G200: P020 | H200: Set de maquillaje | I200: =IF(Tabla2[[#This Row],[precio_unitario]]<=30,"Económico",IF(Tabla2[[#This Row],[precio_unitario]]<=58.49,"Accesible","Caro")) -> Accesible | J200: Perfumería y Belleza | K200: 1 | L200: 55.73 | M200: =INDEX(Tabla3[coste_objetivo], MATCH(Tabla2[[#This Row],[id_producto]], Tabla3[id_producto],0)) -> 33.78 | N200: 0 | O200: =K200*L200*(1-N200) -> 55.73 | P200: =M200*K200 -> 33.78 | Q200: =O200-P200 -> 21.95 | R200: =IFERROR(Q200/O200,0) -> 0.39386327 | S200: Cataluña | T200: online
A201: V01932 | B201: 45918 | C201: =YEAR(Tabla2[[#This Row],[fecha]]) -> 2025 | D201: =MONTH(Tabla2[[#This Row],[fecha]]) -> 9 | E201: =TEXT(Tabla2[[#This Row],[fecha]], "mmmm") -> septiembre | F201: ="T"&ROUNDUP(Tabla2[[#This Row],[mes]]/3,0) -> T3 | G201: P011 | H201: Café en grano 1kg | I201: =IF(Tabla2[[#This Row],[precio_unitario]]<=30,"Económico",IF(Tabla2[[#This Row],[precio_unitario]]<=58.49,"Accesible","Caro")) -> Económico | J201: Alimentación | K201: 2 | L201: 20.82 | M201: 11.21 | N201: 0 | O201: =K201*L201*(1-N201) -> 41.64 | P201: =M201*K201 -> 22.42 | Q201: =O201-P201 -> 19.22 | R201: =IFERROR(Q201/O201,0) -> 0.46157541 | S201: C. Valenciana | T201: tienda_fisica
A202: V01515 | B202: 45843 | C202: =YEAR(Tabla2[[#This Row],[fecha]]) -> 2025 | D202: =MONTH(Tabla2[[#This Row],[fecha]]) -> 7 | E202: =TEXT(Tabla2[[#This Row],[fecha]], "mmmm") -> julio | F202: ="T"&ROUNDUP(Tabla2[[#This Row],[mes]]/3,0) -> T3 | G202: P010 | H202: Cava brut nature | I202: =IF(Tabla2[[#This Row],[precio_unitario]]<=30,"Económico",IF(Tabla2[[#This Row],[precio_unitario]]<=58.49,"Accesible","Caro")) -> Económico | J202: Alimentación | K202: 3 | L202: 15.2 | M202: 11.82 | N202: 0 | O202: =K202*L202*(1-N202) -> 45.6 | P202: =M202*K202 -> 35.46 | Q202: =O202-P202 -> 10.14 | R202: =IFERROR(Q202/O202,0) -> 0.22236842 | S202: Andalucía | T202: tienda_fisica
A203: V02116 | B203: 45617 | C203: =YEAR(Tabla2[[#This Row],[fecha]]) -> 2024 | D203: =MONTH(Tabla2[[#This Row],[fecha]]) -> 11 | E203: =TEXT(Tabla2[[#This Row],[fecha]], "mmmm") -> noviembre | F203: ="T"&ROUNDUP(Tabla2[[#This Row],[mes]]/3,0) -> T4 | G203: P006 | H203: Set de sartenes | I203: =IF(Tabla2[[#This Row],[precio_unitario]]<=30,"Económico",IF(Tabla2[[#This Row],[precio_unitario]]<=58.49,"Accesible","Caro")) -> Accesible | J203: Hogar | K203: 1 | L203: 50.1 | M203: 26.35 | N203: 0 | O203: =K203*L203*(1-N203) -> 50.1 | P203: =M203*K203 -> 26.35 | Q203: =O203-P203 -> 23.75 | R203: =IFERROR(Q203/O203,0) -> 0.4740519 | S203: Baleares | T203: tienda_fisica
A204: V02216 | B204: 45432 | C204: =YEAR(Tabla2[[#This Row],[fecha]]) -> 2024 | D204: =MONTH(Tabla2[[#This Row],[fecha]]) -> 5 | E204: =TEXT(Tabla2[[#This Row],[fecha]], "mmmm") -> mayo | F204: ="T"&ROUNDUP(Tabla2[[#This Row],[mes]]/3,0) -> T2 | G204: P013 | H204: Camiseta básica algodón | I204: =IF(Tabla2[[#This Row],[precio_unitario]]<=30,"Económico",IF(Tabla2[[#This Row],[precio_unitario]]<=58.49,"Accesible","Caro")) -> Caro | J204: Moda | K204: 1 | L204: 73.1 | M204: =INDEX(Tabla3[coste_objetivo], MATCH(Tabla2[[#This Row],[id_producto]], Tabla3[id_producto],0)) -> 47.62 | N204: 0 | O204: =K204*L204*(1-N204) -> 73.1 | P204: =M204*K204 -> 47.62 | Q204: =O204-P204 -> 25.48 | R204: =IFERROR(Q204/O204,0) -> 0.34856361 | S204: C. Valenciana | T204: tienda_fisica
A205: V02037 | B205: 45900 | C205: =YEAR(Tabla2[[#This Row],[fecha]]) -> 2025 | D205: =MONTH(Tabla2[[#This Row],[fecha]]) -> 8 | E205: =TEXT(Tabla2[[#This Row],[fecha]], "mmmm") -> agosto | F205: ="T"&ROUNDUP(Tabla2[[#This Row],[mes]]/3,0) -> T3 | G205: P018 | H205: Crema facial hidratante | I205: =IF(Tabla2[[#This Row],[precio_unitario]]<=30,"Económico",IF(Tabla2[[#This Row],[precio_unitario]]<=58.49,"Accesible","Caro")) -> Accesible | J205: Perfumería y Belleza | K205: 1 | L205: 33.08 | M205: 17.79 | N205: 0 | O205: =K205*L205*(1-N205) -> 33.08 | P205: =M205*K205 -> 17.79 | Q205: =O205-P205 -> 15.29 | R205: =IFERROR(Q205/O205,0) -> 0.46221282 | S205: C. Valenciana | T205: tienda_fisica
A206: V02078 | B206: 45764 | C206: =YEAR(Tabla2[[#This Row],[fecha]]) -> 2025 | D206: =MONTH(Tabla2[[#This Row],[fecha]]) -> 4 | E206: =TEXT(Tabla2[[#This Row],[fecha]], "mmmm") -> abril | F206: ="T"&ROUNDUP(Tabla2[[#This Row],[mes]]/3,0) -> T2 | G206: P020 | H206: Set de maquillaje | I206: =IF(Tabla2[[#This Row],[precio_unitario]]<=30,"Económico",IF(Tabla2[[#This Row],[precio_unitario]]<=58.49,"Accesible","Caro")) -> Accesible | J206: Perfumería y Belleza | K206: 1 | L206: 57.04 | M206: 32.46 | N206: 0 | O206: =K206*L206*(1-N206) -> 57.04 | P206: =M206*K206 -> 32.46 | Q206: =O206-P206 -> 24.58 | R206: =IFERROR(Q206/O206,0) -> 0.43092567 | S206: Cataluña | T206: tienda_fisica
A207: V01465 | B207: 45685 | C207: =YEAR(Tabla2[[#This Row],[fecha]]) -> 2025 | D207: =MONTH(Tabla2[[#This Row],[fecha]]) -> 1 | E207: =TEXT(Tabla2[[#This Row],[fecha]], "mmmm") -> enero | F207: ="T"&ROUNDUP(Tabla2[[#This Row],[mes]]/3,0) -> T1 | G207: P005 | H207: Robot de cocina | I207: =IF(Tabla2[[#This Row],[precio_unitario]]<=30,"Económico",IF(Tabla2[[#This Row],[precio_unitario]]<=58.49,"Accesible","Caro")) -> Accesible | J207: Hogar | K207: 1 | L207: 56.85 | M207: 41.88 | N207: 0 | O207: =K207*L207*(1-N207) -> 56.85 | P207: =M207*K207 -> 41.88 | Q207: =O207-P207 -> 14.97 | R207: =IFERROR(Q207/O207,0) -> 0.26332454 | S207: Aragón | T207: tienda_fisica
A208: V01211 | B208: 45634 | C208: =YEAR(Tabla2[[#This Row],[fecha]]) -> 2024 | D208: =MONTH(Tabla2[[#This Row],[fecha]]) -> 12 | E208: =TEXT(Tabla2[[#This Row],[fecha]], "mmmm") -> diciembre | F208: ="T"&ROUNDUP(Tabla2[[#This Row],[mes]]/3,0) -> T4 | G208: P018 | H208: Crema facial hidratante | I208: =IF(Tabla2[[#This Row],[precio_unitario]]<=30,"Económico",IF(Tabla2[[#This Row],[precio_unitario]]<=58.49,"Accesible","Caro")) -> Accesible | J208: Perfumería y Belleza | K208: 4 | L208: 31.31 | M208: 17.17 | N208: 0 | O208: =K208*L208*(1-N208) -> 125.24 | P208: =M208*K208 -> 68.68 | Q208: =O208-P208 -> 56.56 | R208: =IFERROR(Q208/O208,0) -> 0.4516129 | S208: Baleares | T208: tienda_fisica
A209: V01284 | B209: 45574 | C209: =YEAR(Tabla2[[#This Row],[fecha]]) -> 2024 | D209: =MONTH(Tabla2[[#This Row],[fecha]]) -> 10 | E209: =TEXT(Tabla2[[#This Row],[fecha]], "mmmm") -> octubre | F209: ="T"&ROUNDUP(Tabla2[[#This Row],[mes]]/3,0) -> T4 | G209: P008 | H209: Lámpara LED de pie | I209: =IF(Tabla2[[#This Row],[precio_unitario]]<=30,"Económico",IF(Tabla2[[#This Row],[precio_unitario]]<=58.49,"Accesible","Caro")) -> Caro | J209: Hogar | K209: 5 | L209: 105.45 | M209: 55.78 | N209: 0.12 | O209: =K209*L209*(1-N209) -> 463.98 | P209: =M209*K209 -> 278.9 | Q209: =O209-P209 -> 185.08 | R209: =IFERROR(Q209/O209,0) -> 0.3988965 | S209: Cataluña | T209: online
A210: V00448 | B210: 45785 | C210: =YEAR(Tabla2[[#This Row],[fecha]]) -> 2025 | D210: =MONTH(Tabla2[[#This Row],[fecha]]) -> 5 | E210: =TEXT(Tabla2[[#This Row],[fecha]], "mmmm") -> mayo | F210: ="T"&ROUNDUP(Tabla2[[#This Row],[mes]]/3,0) -> T2 | G210: P002 | H210: Smartwatch | I210: =IF(Tabla2[[#This Row],[precio_unitario]]<=30,"Económico",IF(Tabla2[[#This Row],[precio_unitario]]<=58.49,"Accesible","Caro")) -> Caro | J210: Electrónica | K210: 11 | L210: 74.68 | M210: 46.17 | N210: 0.24 | O210: =K210*L210*(1-N210) -> 624.3248 | P210: =M210*K210 -> 507.87 | Q210: =O210-P210 -> 116.4548 | R210: =IFERROR(Q210/O210,0) -> 0.18652919 | S210: Cataluña | T210: online
A211: V00730 | B211: 45529 | C211: =YEAR(Tabla2[[#This Row],[fecha]]) -> 2024 | D211: =MONTH(Tabla2[[#This Row],[fecha]]) -> 8 | E211: =TEXT(Tabla2[[#This Row],[fecha]], "mmmm") -> agosto | F211: ="T"&ROUNDUP(Tabla2[[#This Row],[mes]]/3,0) -> T3 | G211: P016 | H211: Bolso bandolera | I211: =IF(Tabla2[[#This Row],[precio_unitario]]<=30,"Económico",IF(Tabla2[[#This Row],[precio_unitario]]<=58.49,"Accesible","Caro")) -> Caro | J211: Moda | K211: 2 | L211: 73.36 | M211: 42.62 | N211: 0 | O211: =K211*L211*(1-N211) -> 146.72 | P211: =M211*K211 -> 85.24 | Q211: =O211-P211 -> 61.48 | R211: =IFERROR(Q211/O211,0) -> 0.41902944 | S211: Baleares | T211: tienda_fisica
A212: V02029 | B212: 45377 | C212: =YEAR(Tabla2[[#This Row],[fecha]]) -> 2024 | D212: =MONTH(Tabla2[[#This Row],[fecha]]) -> 3 | E212: =TEXT(Tabla2[[#This Row],[fecha]], "mmmm") -> marzo | F212: ="T"&ROUNDUP(Tabla2[[#This Row],[mes]]/3,0) -> T1 | G212: P014 | H212: Chaqueta acolchada | I212: =IF(Tabla2[[#This Row],[precio_unitario]]<=30,"Económico",IF(Tabla2[[#This Row],[precio_unitario]]<=58.49,"Accesible","Caro")) -> Económico | J212: Moda | K212: 1 | L212: 14.14 | M212: 9.68 | N212: 0 | O212: =K212*L212*(1-N212) -> 14.14 | P212: =M212*K212 -> 9.68 | Q212: =O212-P212 -> 4.46 | R212: =IFERROR(Q212/O212,0) -> 0.31541726 | S212: Aragón | T212: online
A213: V00029 | B213: 45534 | C213: =YEAR(Tabla2[[#This Row],[fecha]]) -> 2024 | D213: =MONTH(Tabla2[[#This Row],[fecha]]) -> 8 | E213: =TEXT(Tabla2[[#This Row],[fecha]], "mmmm") -> agosto | F213: ="T"&ROUNDUP(Tabla2[[#This Row],[mes]]/3,0) -> T3 | G213: P005 | H213: Robot de cocina | I213: =IF(Tabla2[[#This Row],[precio_unitario]]<=30,"Económico",IF(Tabla2[[#This Row],[precio_unitario]]<=58.49,"Accesible","Caro")) -> Accesible | J213: Hogar | K213: 7 | L213: 55.13 | M213: 42.14 | N213: 0 | O213: =K213*L213*(1-N213) -> 385.91 | P213: =M213*K213 -> 294.98 | Q213: =O213-P213 -> 90.93 | R213: =IFERROR(Q213/O213,0) -> 0.23562489 | S213: Aragón | T213: tienda_fisica
A214: V00342 | B214: 45567 | C214: =YEAR(Tabla2[[#This Row],[fecha]]) -> 2024 | D214: =MONTH(Tabla2[[#This Row],[fecha]]) -> 10 | E214: =TEXT(Tabla2[[#This Row],[fecha]], "mmmm") -> octubre | F214: ="T"&ROUNDUP(Tabla2[[#This Row],[mes]]/3,0) -> T4 | G214: P007 | H214: Aspiradora sin cable | I214: =IF(Tabla2[[#This Row],[precio_unitario]]<=30,"Económico",IF(Tabla2[[#This Row],[precio_unitario]]<=58.49,"Accesible","Caro")) -> Económico | J214: Hogar | K214: 9 | L214: 20.43 | M214: 12.87 | N214: 0.09 | O214: =K214*L214*(1-N214) -> 167.3217 | P214: =M214*K214 -> 115.83 | Q214: =O214-P214 -> 51.4917 | R214: =IFERROR(Q214/O214,0) -> 0.30774072 | S214: Madrid | T214: tienda_fisica
A215: V00591 | B215: 45666 | C215: =YEAR(Tabla2[[#This Row],[fecha]]) -> 2025 | D215: =MONTH(Tabla2[[#This Row],[fecha]]) -> 1 | E215: =TEXT(Tabla2[[#This Row],[fecha]], "mmmm") -> enero | F215: ="T"&ROUNDUP(Tabla2[[#This Row],[mes]]/3,0) -> T1 | G215: P003 | H215: Tablet 10" | I215: =IF(Tabla2[[#This Row],[precio_unitario]]<=30,"Económico",IF(Tabla2[[#This Row],[precio_unitario]]<=58.49,"Accesible","Caro")) -> Caro | J215: Electrónica | K215: 1 | L215: =INDEX(Tabla3[precio_venta_recomendado], MATCH(Tabla2[[#This Row],[id_producto]], Tabla3[id_producto], 0)) -> 177.72 | M215: 95.58 | N215: 0.06 | O215: =K215*L215*(1-N215) -> 167.0568 | P215: =M215*K215 -> 95.58 | Q215: =O215-P215 -> 71.4768 | R215: =IFERROR(Q215/O215,0) -> 0.42785927 | S215: C. Valenciana | T215: tienda_fisica
A216: V00603 | B216: 45648 | C216: =YEAR(Tabla2[[#This Row],[fecha]]) -> 2024 | D216: =MONTH(Tabla2[[#This Row],[fecha]]) -> 12 | E216: =TEXT(Tabla2[[#This Row],[fecha]], "mmmm") -> diciembre | F216: ="T"&ROUNDUP(Tabla2[[#This Row],[mes]]/3,0) -> T4 | G216: P010 | H216: Cava brut nature | I216: =IF(Tabla2[[#This Row],[precio_unitario]]<=30,"Económico",IF(Tabla2[[#This Row],[precio_unitario]]<=58.49,"Accesible","Caro")) -> Económico | J216: Alimentación | K216: 1 | L216: 17.59 | M216: 11.58 | N216: 0 | O216: =K216*L216*(1-N216) -> 17.59 | P216: =M216*K216 -> 11.58 | Q216: =O216-P216 -> 6.01 | R216: =IFERROR(Q216/O216,0) -> 0.3416714 | S216: C. Valenciana | T216: tienda_fisica
A217: V00514 | B217: 45617 | C217: =YEAR(Tabla2[[#This Row],[fecha]]) -> 2024 | D217: =MONTH(Tabla2[[#This Row],[fecha]]) -> 11 | E217: =TEXT(Tabla2[[#This Row],[fecha]], "mmmm") -> noviembre | F217: ="T"&ROUNDUP(Tabla2[[#This Row],[mes]]/3,0) -> T4 | G217: P006 | H217: Set de sartenes | I217: =IF(Tabla2[[#This Row],[precio_unitario]]<=30,"Económico",IF(Tabla2[[#This Row],[precio_unitario]]<=58.49,"Accesible","Caro")) -> Accesible | J217: Hogar | K217: 5 | L217: 49.26 | M217: 25.69 | N217: 0.13 | O217: =K217*L217*(1-N217) -> 214.281 | P217: =M217*K217 -> 128.45 | Q217: =O217-P217 -> 85.831 | R217: =IFERROR(Q217/O217,0) -> 0.40055348 | S217: Cataluña | T217: tienda_fisica
A218: V01587 | B218: 45955 | C218: =YEAR(Tabla2[[#This Row],[fecha]]) -> 2025 | D218: =MONTH(Tabla2[[#This Row],[fecha]]) -> 10 | E218: =TEXT(Tabla2[[#This Row],[fecha]], "mmmm") -> octubre | F218: ="T"&ROUNDUP(Tabla2[[#This Row],[mes]]/3,0) -> T4 | G218: P017 | H218: Perfume eau de parfum 90ml | I218: =IF(Tabla2[[#This Row],[precio_unitario]]<=30,"Económico",IF(Tabla2[[#This Row],[precio_unitario]]<=58.49,"Accesible","Caro")) -> Accesible | J218: Perfumería y Belleza | K218: 1 | L218: 50.88 | M218: 22.96 | N218: 0 | O218: =K218*L218*(1-N218) -> 50.88 | P218: =M218*K218 -> 22.96 | Q218: =O218-P218 -> 27.92 | R218: =IFERROR(Q218/O218,0) -> 0.54874214 | S218: Cataluña | T218: online
A219: V02267 | B219: 45595 | C219: =YEAR(Tabla2[[#This Row],[fecha]]) -> 2024 | D219: =MONTH(Tabla2[[#This Row],[fecha]]) -> 10 | E219: =TEXT(Tabla2[[#This Row],[fecha]], "mmmm") -> octubre | F219: ="T"&ROUNDUP(Tabla2[[#This Row],[mes]]/3,0) -> T4 | G219: P005 | H219: Robot de cocina | I219: =IF(Tabla2[[#This Row],[precio_unitario]]<=30,"Económico",IF(Tabla2[[#This Row],[precio_unitario]]<=58.49,"Accesible","Caro")) -> Accesible | J219: Hogar | K219: 1 | L219: 58.11 | M219: 40.07 | N219: 0 | O219: =K219*L219*(1-N219) -> 58.11 | P219: =M219*K219 -> 40.07 | Q219: =O219-P219 -> 18.04 | R219: =IFERROR(Q219/O219,0) -> 0.31044571 | S219: Aragón | T219: online
A220: V01833 | B220: 45634 | C220: =YEAR(Tabla2[[#This Row],[fecha]]) -> 2024 | D220: =MONTH(Tabla2[[#This Row],[fecha]]) -> 12 | E220: =TEXT(Tabla2[[#This Row],[fecha]], "mmmm") -> diciembre | F220: ="T"&ROUNDUP(Tabla2[[#This Row],[mes]]/3,0) -> T4 | G220: P011 | H220: Café en grano 1kg | I220: =IF(Tabla2[[#This Row],[precio_unitario]]<=30,"Económico",IF(Tabla2[[#This Row],[precio_unitario]]<=58.49,"Accesible","Caro")) -> Económico | J220: Alimentación | K220: 2 | L220: 20.94 | M220: 10.92 | N220: 0 | O220: =K220*L220*(1-N220) -> 41.88 | P220: =M220*K220 -> 21.84 | Q220: =O220-P220 -> 20.04 | R220: =IFERROR(Q220/O220,0) -> 0.47851003 | S220: Cataluña | T220: tienda_fisica
A221: V01481 | B221: 45512 | C221: =YEAR(Tabla2[[#This Row],[fecha]]) -> 2024 | D221: =MONTH(Tabla2[[#This Row],[fecha]]) -> 8 | E221: =TEXT(Tabla2[[#This Row],[fecha]], "mmmm") -> agosto | F221: ="T"&ROUNDUP(Tabla2[[#This Row],[mes]]/3,0) -> T3 | G221: P001 | H221: Auriculares inalámbricos | I221: =IF(Tabla2[[#This Row],[precio_unitario]]<=30,"Económico",IF(Tabla2[[#This Row],[precio_unitario]]<=58.49,"Accesible","Caro")) -> Caro | J221: Electrónica | K221: 1 | L221: 127.87 | M221: 86.41 | N221: 0 | O221: =K221*L221*(1-N221) -> 127.87 | P221: =M221*K221 -> 86.41 | Q221: =O221-P221 -> 41.46 | R221: =IFERROR(Q221/O221,0) -> 0.32423555 | S221: C. Valenciana | T221: tienda_fisica
...

Sheet TD01_volumen_ventas
A1: año | B1: 2025
A2: comunidad_autonoma | B2: Cataluña
A4: Rótulos de fila | B4: Suma de cantidad
A5: Smartwatch | B5: 80
A6: Chaqueta acolchada | B6: 76
A7: Robot de cocina | B7: 71
A8: Aceite de oliva virgen extra 1L | B8: 70
A9: Crema facial hidratante | B9: 69
A10: Total general | B10: 366

Sheet TD02_ingresos_costes_beneficios
A1: año | B1: 2025
A2: comunidad_autonoma | B2: Cataluña
B4: Valores
A5: Rótulos de fila | B5: Suma de ingresos | C5: Suma de costes | D5: Promedio de beneficio
A6: Tablet 10" | B6: 10466.429 | C6: 5775.8 | D6: 223.36329
A7: Altavoz Bluetooth | B7: 8258.2093 | C7: 5579.13 | D7: 148.83774
A8: Auriculares inalámbricos | B8: 8029.3124 | C8: 5699.8 | D8: 116.47562
A9: Smartwatch | B9: 5535.6745 | C9: 3770.89 | D9: 65.362389
A10: Lámpara LED de pie | B10: 5394.3362 | C10: 3107.35 | D10: 91.479448
A11: Total general | B11: 37683.961 | C11: 23932.97 | D11: 123.88281

Sheet TD03_beneficios_pct
A1: año | B1: 2025
A2: comunidad_autonoma | B2: Cataluña
A4: Rótulos de fila | B4: Promedio de beneficio_pct
A5: Perfume eau de parfum 90ml | B5: 0.52511543
A6: Bolso bandolera | B6: 0.46525942
A7: Tablet 10" | B7: 0.43989436
A8: Café en grano 1kg | B8: 0.43801594
A9: Aceite de oliva virgen extra 1L | B9: 0.43594402
A10: Total general | B10: 0.45588214

Sheet TD04_gama
A1: año | B1: 2025
A2: comunidad_autonoma | B2: Cataluña
A4: Rótulos de fila | B4: Promedio de precio_unitario
A5: Económico
A6: Aceite de oliva virgen extra 1L | B6: 7.8492593
A7: Aspiradora sin cable | B7: 20.15381
A8: Café en grano 1kg | B8: 21.462308
A9: Cava brut nature | B9: 16.393571
A10: Chaqueta acolchada | B10: 14.084643
A11: Chocolate a la taza 500g | B11: 8.782
A12: Crema facial hidratante | B12: 29.713333
A13: Accesible
A14: Champú reparador | B14: 56.924444
A15: Crema facial hidratante | B15: 31.767308
A16: Perfume eau de parfum 90ml | B16: 49.523846
A17: Robot de cocina | B17: 56.762
A18: Set de maquillaje | B18: 57.19
A19: Set de sartenes | B19: 47.638824
A20: Caro
A21: Altavoz Bluetooth | B21: 159.10111
A22: Auriculares inalámbricos | B22: 121.479
A23: Bolso bandolera | B23: 77.850455
A24: Camiseta básica algodón | B24: 75.335833
A25: Champú reparador | B25: 61.852
A26: Lámpara LED de pie | B26: 103.6568
A27: Robot de cocina | B27: 61.779231
A28: Set de maquillaje | B28: 61.972308
A29: Smartwatch | B29: 74.172593
A30: Tablet 10" | B30: 174.10905
A31: Zapatillas running | B31: 78.407895
A32: Total general | B32: 62.165179

Sheet TD05_analisis_productos
A1: año | B1: 2025
A2: comunidad_autonoma | B2: Cataluña
A3: producto | B3: Perfume eau de parfum 90ml
A5: Valores
A6: Suma de cantidad | B6: Suma de ingresos | C6: Promedio de beneficio_pct
A7: 19 | B7: 909.9696 | C7: 0.52511543
A10: año | B10: 2025
A11: comunidad_autonoma | B11: Cataluña
A12: producto | B12: Tablet 10"
A14: Valores
A15: Suma de cantidad | B15: Suma de ingresos | C15: Promedio de beneficio_pct
A16: 61 | B16: 10466.429 | C16: 0.43989436
A18: año | B18: 2025
A19: comunidad_autonoma | B19: Cataluña
A20: producto | B20: Smartwatch
A22: Valores
A23: Suma de cantidad | B23: Suma de ingresos | C23: Promedio de beneficio_pct
A24: 80 | B24: 5535.6745 | C24: 0.32815013

Sheet TD06_beneficios_smartwatch
A1: año | B1: 2025
A2: comunidad_autonoma | B2: Cataluña
A4: Rótulos de fila | B4: Promedio de beneficio_pct
A5: Alimentación | B5: 0.37248657
A6: Café en grano 1kg | B6: 0.43801594
A7: Aceite de oliva virgen extra 1L | B7: 0.43594402
A8: Chocolate a la taza 500g | B8: 0.31482135
A9: Cava brut nature | B9: 0.29222926
A10: Electrónica | B10: 0.3405551
A11: Tablet 10" | B11: 0.43989436
A12: Smartwatch | B12: 0.32815013
A13: Altavoz Bluetooth | B13: 0.3078361
A14: Auriculares inalámbricos | B14: 0.28244268
A15: Hogar | B15: 0.3684397
A16: Lámpara LED de pie | B16: 0.41967311
... A30: Total general | B30: 0.3778581

Sheet KPIS
B2: KPIS DE NEGOCIO | C2: CATALUÑA Y 2025
B4: Unidades Totales Vendidas | C4: =GETPIVOTDATA("cantidad",TD01_volumen_ventas!$A$4) -> 366
B6: Ingresos Totales | C6: =GETPIVOTDATA("Suma de ingresos",TD02_ingresos_costes_beneficios!$A$4) -> 37683.961
B8: Costes Totales | C8: =GETPIVOTDATA("Suma de costes",TD02_ingresos_costes_beneficios!$A$4) -> 23932.97
B10: Beneficio Promedio | C10: =GETPIVOTDATA("Promedio de beneficio",TD02_ingresos_costes_beneficios!$A$4) -> 123.88281
B12: Margen de Beneficio Promedio | C12: =GETPIVOTDATA("beneficio_pct",TD03_beneficios_pct!$A$4) -> 0.45588214

Sheet TOP_productos
B2: TOP 1 PRODUCTOS DE NEGOCIO | C2: CATALUÑA Y 2025
B4: Productos Volumen | C4: =TD01_volumen_ventas!A5 -> Smartwatch
B5: Producto ingresos | C5: =TD02_ingresos_costes_beneficios!$A$6 -> Tablet 10"
B6: Producto Costes | C6: =TD02_ingresos_costes_beneficios!$A$6 -> Tablet 10"
B7: Producto Beneficio promedio | C7: =TD03_beneficios_pct!A5 -> Perfume eau de parfum 90ml

Sheet informe_final
F1: INFORME DE PRODUCTOS DE NEGOCIO: CATALUÑA Y 2025
C3: Producto de Volumen | D3: Estrategia | F3: Producto de Ingresos | G3: Estrategia | I3: Producto de beneficios | J3: Estrategia
C4: Smartwatch | D4: Mantener el producto como referencia de volumen, evitando incrementos de precio | F4: Tablet 10 | G4: Potenciar su promoción entre clientes con mayor poder adquisitivo. | I4: Perfume eau de parfum 90ml | J4: Oportunidad de aumentar su visibilidad mediante acciones de publicidad y promoción.
C6: Producto | D6: Suma de cantidad | F6: Rótulos de fila | G6: Suma de ingresos | I6: Rótulos de fila | J6: Promedio de beneficio_pct
C7: Smartwatch | D7: 80 | F7: Tablet 10" | G7: 10466.429 | I7: Perfume eau de parfum 90ml | J7: 0.52511543
C8: Chaqueta acolchada | D8: 76 | F8: Altavoz Bluetooth | G8: 8258.2093 | I8: Bolso bandolera | J8: 0.46525942
C9: Robot de cocina | D9: 71 | F9: Auriculares inalámbricos | G9: 8029.3124 | I9: Tablet 10" | J9: 0.43989436
C10: Aceite de oliva virgen extra 1L | D10: 70 | F10: Smartwatch | G10: 5535.6745 | I10: Café en grano 1kg | J10: 0.43801594
C11: Crema facial hidratante | D11: 69 | F11: Lámpara LED de pie | G11: 5394.3362 | I11: Aceite de oliva virgen extra 1L | J11: 0.43594402
C12: Total general | D12: 366 | F12: Total general | G12: 37683.961 | I12: Total general | J12: 0.45588214
